[
  {
    "reference": "US-0139",
    "name": "Eufaula National Wildlife Refuge",
    "latitude": 31.9959,
    "longitude": -85.0948,
    "grid": "EM71kx",
    "locationDesc": "US-AL,US-GA",
    "attempts": 86,
    "activations": 85,
    "qsos": 2658
  },
  {
    "reference": "US-0259",
    "name": "Banks Lake National Wildlife Refuge",
    "latitude": 31.0351,
    "longitude": -83.0956,
    "grid": "EM81ka",
    "locationDesc": "US-GA",
    "attempts": 67,
    "activations": 63,
    "qsos": 2789
  },
  {
    "reference": "US-0260",
    "name": "Blackbeard Island National Wildlife Refuge",
    "latitude": 31.5187,
    "longitude": -81.1962,
    "grid": "EM91jm",
    "locationDesc": "US-GA",
    "attempts": 9,
    "activations": 9,
    "qsos": 572
  },
  {
    "reference": "US-0261",
    "name": "Bond Swamp National Wildlife Refuge",
    "latitude": 32.7394,
    "longitude": -83.5628,
    "grid": "EM82fr",
    "locationDesc": "US-GA",
    "attempts": 85,
    "activations": 85,
    "qsos": 4016
  },
  {
    "reference": "US-0262",
    "name": "Harris Neck National Wildlife Refuge",
    "latitude": 31.6312,
    "longitude": -81.2678,
    "grid": "EM91ip",
    "locationDesc": "US-GA",
    "attempts": 85,
    "activations": 83,
    "qsos": 3590
  },
  {
    "reference": "US-0263",
    "name": "Okefenokee National Wildlife Refuge",
    "latitude": 30.7383,
    "longitude": -82.14,
    "grid": "EM80wr",
    "locationDesc": "US-GA",
    "attempts": 79,
    "activations": 79,
    "qsos": 2691
  },
  {
    "reference": "US-0264",
    "name": "Piedmont National Wildlife Refuge",
    "latitude": 33.111,
    "longitude": -83.679,
    "grid": "EM83dc",
    "locationDesc": "US-GA",
    "attempts": 67,
    "activations": 66,
    "qsos": 2658
  },
  {
    "reference": "US-0266",
    "name": "Wassaw National Wildlife Refuge",
    "latitude": 31.8945,
    "longitude": -80.9922,
    "grid": "EM91mv",
    "locationDesc": "US-GA",
    "attempts": 18,
    "activations": 18,
    "qsos": 758
  },
  {
    "reference": "US-0267",
    "name": "Wolf Island National Wildlife Refuge",
    "latitude": 31.3501,
    "longitude": -81.301,
    "grid": "EM91ii",
    "locationDesc": "US-GA",
    "attempts": 7,
    "activations": 7,
    "qsos": 384
  },
  {
    "reference": "US-0522",
    "name": "Savannah National Wildlife Refuge",
    "latitude": 32.1655,
    "longitude": -81.1514,
    "grid": "EM92kd",
    "locationDesc": "US-GA,US-SC",
    "attempts": 571,
    "activations": 560,
    "qsos": 20370
  },
  {
    "reference": "US-0636",
    "name": "Jekyll Island State Park",
    "latitude": 31.04,
    "longitude": -81.42,
    "grid": "EM91ga",
    "locationDesc": "US-GA",
    "attempts": 280,
    "activations": 256,
    "qsos": 11310
  },
  {
    "reference": "US-0662",
    "name": "Chattahoochee River National Recreation Area",
    "latitude": 33.9999,
    "longitude": -84.2491,
    "grid": "EM73vx",
    "locationDesc": "US-GA",
    "attempts": 1889,
    "activations": 1782,
    "qsos": 59358
  },
  {
    "reference": "US-0663",
    "name": "Cumberland Island National Seashore",
    "latitude": 30.7651,
    "longitude": -81.4681,
    "grid": "EM90gs",
    "locationDesc": "US-GA",
    "attempts": 43,
    "activations": 42,
    "qsos": 2118
  },
  {
    "reference": "US-0711",
    "name": "Kennesaw Mountain National Battlefield",
    "latitude": 33.9844,
    "longitude": -84.5781,
    "grid": "EM73rx",
    "locationDesc": "US-GA",
    "attempts": 513,
    "activations": 485,
    "qsos": 18867
  },
  {
    "reference": "US-0716",
    "name": "Chickamauga and Chattanooga National Military Park",
    "latitude": 34.9405,
    "longitude": -85.2598,
    "grid": "EM74iw",
    "locationDesc": "US-GA,US-TN",
    "attempts": 627,
    "activations": 613,
    "qsos": 21510
  },
  {
    "reference": "US-0799",
    "name": "Andersonville National Historic Site",
    "latitude": 32.1896,
    "longitude": -84.1244,
    "grid": "EM72we",
    "locationDesc": "US-GA",
    "attempts": 66,
    "activations": 65,
    "qsos": 2358
  },
  {
    "reference": "US-0837",
    "name": "Jimmy Carter National Historic Site",
    "latitude": 32.0265,
    "longitude": -84.4246,
    "grid": "EM72sa",
    "locationDesc": "US-GA",
    "attempts": 51,
    "activations": 50,
    "qsos": 1805
  },
  {
    "reference": "US-0846",
    "name": "Martin Luther King Jr. National Historic Site",
    "latitude": 33.7569,
    "longitude": -84.3736,
    "grid": "EM73ts",
    "locationDesc": "US-GA",
    "attempts": 164,
    "activations": 160,
    "qsos": 3435
  },
  {
    "reference": "US-0926",
    "name": "Fort Frederica National Monument",
    "latitude": 31.2231,
    "longitude": -81.3893,
    "grid": "EM91hf",
    "locationDesc": "US-GA",
    "attempts": 66,
    "activations": 64,
    "qsos": 1843
  },
  {
    "reference": "US-0930",
    "name": "Fort Pulaski National Monument",
    "latitude": 32.0271,
    "longitude": -80.8905,
    "grid": "EM92na",
    "locationDesc": "US-GA",
    "attempts": 339,
    "activations": 327,
    "qsos": 16347
  },
  {
    "reference": "US-0952",
    "name": "Ocmulgee National Monument",
    "latitude": 32.8396,
    "longitude": -83.6034,
    "grid": "EM82eu",
    "locationDesc": "US-GA",
    "attempts": 118,
    "activations": 117,
    "qsos": 3634
  },
  {
    "reference": "US-2165",
    "name": "A. H. Stephens State Park",
    "latitude": 33.562,
    "longitude": -82.8955,
    "grid": "EM83nn",
    "locationDesc": "US-GA",
    "attempts": 124,
    "activations": 118,
    "qsos": 5222
  },
  {
    "reference": "US-2166",
    "name": "Amicalola Falls State Park",
    "latitude": 34.5683,
    "longitude": -84.2436,
    "grid": "EM74vn",
    "locationDesc": "US-GA",
    "attempts": 294,
    "activations": 284,
    "qsos": 9180
  },
  {
    "reference": "US-2167",
    "name": "Black Rock Mountain State Park",
    "latitude": 34.9107,
    "longitude": -83.4116,
    "grid": "EM84hv",
    "locationDesc": "US-GA",
    "attempts": 359,
    "activations": 324,
    "qsos": 11882
  },
  {
    "reference": "US-2168",
    "name": "Chattahoochee Bend State Park",
    "latitude": 33.4299,
    "longitude": -84.9896,
    "grid": "EM73mk",
    "locationDesc": "US-GA",
    "attempts": 268,
    "activations": 252,
    "qsos": 11476
  },
  {
    "reference": "US-2169",
    "name": "Cloudland Canyon State Park",
    "latitude": 34.8395,
    "longitude": -85.484,
    "grid": "EM74gu",
    "locationDesc": "US-GA",
    "attempts": 673,
    "activations": 655,
    "qsos": 29157
  },
  {
    "reference": "US-2170",
    "name": "Crooked River State Park",
    "latitude": 30.8407,
    "longitude": -81.5514,
    "grid": "EM90fu",
    "locationDesc": "US-GA",
    "attempts": 378,
    "activations": 361,
    "qsos": 20143
  },
  {
    "reference": "US-2171",
    "name": "Don Carter State Park",
    "latitude": 34.3907,
    "longitude": -83.7491,
    "grid": "EM84dj",
    "locationDesc": "US-GA",
    "attempts": 1288,
    "activations": 1250,
    "qsos": 42516
  },
  {
    "reference": "US-2172",
    "name": "Elijah Clark State Park",
    "latitude": 33.8497,
    "longitude": -82.3975,
    "grid": "EM83tu",
    "locationDesc": "US-GA",
    "attempts": 124,
    "activations": 119,
    "qsos": 8344
  },
  {
    "reference": "US-2173",
    "name": "F.D. Roosevelt State Park",
    "latitude": 32.8411,
    "longitude": -84.7452,
    "grid": "EM72pu",
    "locationDesc": "US-GA",
    "attempts": 549,
    "activations": 520,
    "qsos": 25119
  },
  {
    "reference": "US-2174",
    "name": "Florence Marina State Park",
    "latitude": 32.087,
    "longitude": -85.0416,
    "grid": "EM72lc",
    "locationDesc": "US-GA",
    "attempts": 85,
    "activations": 84,
    "qsos": 3745
  },
  {
    "reference": "US-2175",
    "name": "Fort McAllister State Park",
    "latitude": 31.885,
    "longitude": -81.1815,
    "grid": "EM91jv",
    "locationDesc": "US-GA",
    "attempts": 352,
    "activations": 342,
    "qsos": 17544
  },
  {
    "reference": "US-2176",
    "name": "Fort Mountain State Park",
    "latitude": 34.7594,
    "longitude": -84.6922,
    "grid": "EM74ps",
    "locationDesc": "US-GA",
    "attempts": 310,
    "activations": 287,
    "qsos": 14154
  },
  {
    "reference": "US-2177",
    "name": "Fort Yargo State Park",
    "latitude": 33.9807,
    "longitude": -83.7367,
    "grid": "EM83dx",
    "locationDesc": "US-GA",
    "attempts": 1417,
    "activations": 1370,
    "qsos": 43389
  },
  {
    "reference": "US-2178",
    "name": "General Coffee State Park",
    "latitude": 31.5088,
    "longitude": -82.7553,
    "grid": "EM81om",
    "locationDesc": "US-GA",
    "attempts": 123,
    "activations": 118,
    "qsos": 5897
  },
  {
    "reference": "US-2179",
    "name": "George L. Smith State Park",
    "latitude": 32.5586,
    "longitude": -82.1197,
    "grid": "EM82wn",
    "locationDesc": "US-GA",
    "attempts": 155,
    "activations": 143,
    "qsos": 5243
  },
  {
    "reference": "US-2180",
    "name": "George T. Bagby State Park",
    "latitude": 31.6651,
    "longitude": -85.0577,
    "grid": "EM71lp",
    "locationDesc": "US-GA",
    "attempts": 68,
    "activations": 68,
    "qsos": 3001
  },
  {
    "reference": "US-2181",
    "name": "Georgia Veterans State Park",
    "latitude": 31.9683,
    "longitude": -83.9124,
    "grid": "EM81bx",
    "locationDesc": "US-GA",
    "attempts": 207,
    "activations": 202,
    "qsos": 15218
  },
  {
    "reference": "US-2182",
    "name": "Jack Hill State Park",
    "latitude": 32.0825,
    "longitude": -82.1227,
    "grid": "EM82wb",
    "locationDesc": "US-GA",
    "attempts": 104,
    "activations": 103,
    "qsos": 5076
  },
  {
    "reference": "US-2183",
    "name": "Hamburg State Park",
    "latitude": 33.2065,
    "longitude": -82.7785,
    "grid": "EM83oe",
    "locationDesc": "US-GA",
    "attempts": 89,
    "activations": 84,
    "qsos": 3657
  },
  {
    "reference": "US-2184",
    "name": "Hard Labor Creek State Park",
    "latitude": 33.6673,
    "longitude": -83.6061,
    "grid": "EM83eq",
    "locationDesc": "US-GA",
    "attempts": 618,
    "activations": 596,
    "qsos": 27470
  },
  {
    "reference": "US-2185",
    "name": "High Falls State Park",
    "latitude": 33.1824,
    "longitude": -84.0141,
    "grid": "EM73xe",
    "locationDesc": "US-GA",
    "attempts": 201,
    "activations": 195,
    "qsos": 8082
  },
  {
    "reference": "US-2186",
    "name": "Indian Springs State Park",
    "latitude": 33.2477,
    "longitude": -83.9205,
    "grid": "EM83af",
    "locationDesc": "US-GA",
    "attempts": 197,
    "activations": 181,
    "qsos": 7203
  },
  {
    "reference": "US-2187",
    "name": "James H. (Sloppy) Floyd State Park",
    "latitude": 34.4399,
    "longitude": -85.3372,
    "grid": "EM74hk",
    "locationDesc": "US-GA",
    "attempts": 273,
    "activations": 263,
    "qsos": 14771
  },
  {
    "reference": "US-2188",
    "name": "Laura S. Walker State Park",
    "latitude": 31.1441,
    "longitude": -82.2138,
    "grid": "EM81vd",
    "locationDesc": "US-GA",
    "attempts": 389,
    "activations": 365,
    "qsos": 17683
  },
  {
    "reference": "US-2189",
    "name": "Little Ocmulgee State Park",
    "latitude": 32.0916,
    "longitude": -82.8848,
    "grid": "EM82nc",
    "locationDesc": "US-GA",
    "attempts": 143,
    "activations": 142,
    "qsos": 6058
  },
  {
    "reference": "US-2190",
    "name": "Magnolia Springs State Park",
    "latitude": 32.8807,
    "longitude": -81.9561,
    "grid": "EM92av",
    "locationDesc": "US-GA",
    "attempts": 118,
    "activations": 112,
    "qsos": 4835
  },
  {
    "reference": "US-2191",
    "name": "Mistletoe State Park",
    "latitude": 33.646,
    "longitude": -82.3798,
    "grid": "EM83tp",
    "locationDesc": "US-GA",
    "attempts": 242,
    "activations": 225,
    "qsos": 11443
  },
  {
    "reference": "US-2192",
    "name": "Moccasin Creek State Park",
    "latitude": 34.844,
    "longitude": -83.588,
    "grid": "EM84eu",
    "locationDesc": "US-GA",
    "attempts": 129,
    "activations": 128,
    "qsos": 4282
  },
  {
    "reference": "US-2193",
    "name": "Panola Mountain State Park",
    "latitude": 33.625,
    "longitude": -84.1715,
    "grid": "EM73vp",
    "locationDesc": "US-GA",
    "attempts": 378,
    "activations": 362,
    "qsos": 15967
  },
  {
    "reference": "US-2194",
    "name": "Red Top Mountain State Park",
    "latitude": 34.1479,
    "longitude": -84.7043,
    "grid": "EM74pd",
    "locationDesc": "US-GA",
    "attempts": 1016,
    "activations": 943,
    "qsos": 52189
  },
  {
    "reference": "US-2195",
    "name": "Reed Bingham State Park",
    "latitude": 31.1609,
    "longitude": -83.5372,
    "grid": "EM81fd",
    "locationDesc": "US-GA",
    "attempts": 585,
    "activations": 563,
    "qsos": 30531
  },
  {
    "reference": "US-2196",
    "name": "Richard B. Russell State Park",
    "latitude": 34.1781,
    "longitude": -82.7614,
    "grid": "EM84oe",
    "locationDesc": "US-GA",
    "attempts": 102,
    "activations": 100,
    "qsos": 4367
  },
  {
    "reference": "US-2197",
    "name": "Seminole State Park",
    "latitude": 30.8095,
    "longitude": -84.8779,
    "grid": "EM70nt",
    "locationDesc": "US-GA",
    "attempts": 70,
    "activations": 68,
    "qsos": 3551
  },
  {
    "reference": "US-2198",
    "name": "Skidaway Island State Park",
    "latitude": 31.9526,
    "longitude": -81.0561,
    "grid": "EM91lw",
    "locationDesc": "US-GA",
    "attempts": 384,
    "activations": 377,
    "qsos": 21977
  },
  {
    "reference": "US-2199",
    "name": "Smithgall Woods State Park",
    "latitude": 34.6918,
    "longitude": -83.7694,
    "grid": "EM84cq",
    "locationDesc": "US-GA",
    "attempts": 173,
    "activations": 166,
    "qsos": 4901
  },
  {
    "reference": "US-2200",
    "name": "Stephen C Foster State Park",
    "latitude": 30.8219,
    "longitude": -82.3648,
    "grid": "EM80tt",
    "locationDesc": "US-GA",
    "attempts": 82,
    "activations": 82,
    "qsos": 3550
  },
  {
    "reference": "US-2201",
    "name": "Sweetwater Creek State Park",
    "latitude": 33.7542,
    "longitude": -84.6395,
    "grid": "EM73qs",
    "locationDesc": "US-GA",
    "attempts": 368,
    "activations": 356,
    "qsos": 14538
  },
  {
    "reference": "US-2202",
    "name": "Tallulah Gorge State Park",
    "latitude": 34.7428,
    "longitude": -83.3963,
    "grid": "EM84hr",
    "locationDesc": "US-GA",
    "attempts": 187,
    "activations": 170,
    "qsos": 5157
  },
  {
    "reference": "US-2203",
    "name": "Tugaloo State Park",
    "latitude": 34.4942,
    "longitude": -83.0638,
    "grid": "EM84ll",
    "locationDesc": "US-GA",
    "attempts": 278,
    "activations": 264,
    "qsos": 12676
  },
  {
    "reference": "US-2204",
    "name": "Unicoi State Park",
    "latitude": 34.7226,
    "longitude": -83.7224,
    "grid": "EM84dr",
    "locationDesc": "US-GA",
    "attempts": 255,
    "activations": 238,
    "qsos": 7512
  },
  {
    "reference": "US-2205",
    "name": "Victoria Bryant State Park",
    "latitude": 34.3011,
    "longitude": -83.1598,
    "grid": "EM84kh",
    "locationDesc": "US-GA",
    "attempts": 253,
    "activations": 245,
    "qsos": 9156
  },
  {
    "reference": "US-2206",
    "name": "Vogel State Park",
    "latitude": 34.767,
    "longitude": -83.9197,
    "grid": "EM84as",
    "locationDesc": "US-GA",
    "attempts": 310,
    "activations": 294,
    "qsos": 14285
  },
  {
    "reference": "US-2207",
    "name": "Watson Mill Bridge State Park",
    "latitude": 34.0261,
    "longitude": -83.0734,
    "grid": "EM84la",
    "locationDesc": "US-GA",
    "attempts": 731,
    "activations": 701,
    "qsos": 34597
  },
  {
    "reference": "US-3715",
    "name": "Etowah Indian Mounds State Historic Site",
    "latitude": 34.128,
    "longitude": -84.8071,
    "grid": "EM74od",
    "locationDesc": "US-GA",
    "attempts": 190,
    "activations": 186,
    "qsos": 6760
  },
  {
    "reference": "US-3716",
    "name": "Fort King George State Historic Site",
    "latitude": 31.3638,
    "longitude": -81.4149,
    "grid": "EM91hi",
    "locationDesc": "US-GA",
    "attempts": 64,
    "activations": 61,
    "qsos": 1366
  },
  {
    "reference": "US-3717",
    "name": "Fort Morris State Historic Site",
    "latitude": 31.7601,
    "longitude": -81.2895,
    "grid": "EM91is",
    "locationDesc": "US-GA",
    "attempts": 174,
    "activations": 165,
    "qsos": 7849
  },
  {
    "reference": "US-3718",
    "name": "Hardman Farm State Historic Site",
    "latitude": 34.685,
    "longitude": -83.7083,
    "grid": "EM84dq",
    "locationDesc": "US-GA",
    "attempts": 186,
    "activations": 183,
    "qsos": 4719
  },
  {
    "reference": "US-3719",
    "name": "Hofwyl-Broadfield Plantation State Historic Site",
    "latitude": 31.305,
    "longitude": -81.4602,
    "grid": "EM91gh",
    "locationDesc": "US-GA",
    "attempts": 111,
    "activations": 102,
    "qsos": 2439
  },
  {
    "reference": "US-3720",
    "name": "Jarrell Plantation State Historic Site",
    "latitude": 33.0531,
    "longitude": -83.7229,
    "grid": "EM83db",
    "locationDesc": "US-GA",
    "attempts": 60,
    "activations": 60,
    "qsos": 1494
  },
  {
    "reference": "US-3721",
    "name": "Jefferson Davis Memorial State Historic Site",
    "latitude": 31.6646,
    "longitude": -83.3867,
    "grid": "EM81hp",
    "locationDesc": "US-GA",
    "attempts": 50,
    "activations": 48,
    "qsos": 1106
  },
  {
    "reference": "US-3722",
    "name": "New Echota State Historic Site",
    "latitude": 34.5413,
    "longitude": -84.91,
    "grid": "EM74nm",
    "locationDesc": "US-GA",
    "attempts": 171,
    "activations": 166,
    "qsos": 5966
  },
  {
    "reference": "US-3723",
    "name": "Pickett's Mill Battlefield State Historic Site",
    "latitude": 33.974,
    "longitude": -84.7591,
    "grid": "EM73ox",
    "locationDesc": "US-GA",
    "attempts": 299,
    "activations": 290,
    "qsos": 9933
  },
  {
    "reference": "US-3724",
    "name": "Roosevelts Little White House State Historic Site",
    "latitude": 32.8824,
    "longitude": -84.6857,
    "grid": "EM72pv",
    "locationDesc": "US-GA",
    "attempts": 101,
    "activations": 100,
    "qsos": 3267
  },
  {
    "reference": "US-3725",
    "name": "Wormsloe State Historic Site",
    "latitude": 31.9806,
    "longitude": -81.0692,
    "grid": "EM91lx",
    "locationDesc": "US-GA",
    "attempts": 318,
    "activations": 311,
    "qsos": 14912
  },
  {
    "reference": "US-3726",
    "name": "Kolomoki Mounds State Park",
    "latitude": 31.4729,
    "longitude": -84.9435,
    "grid": "EM71ml",
    "locationDesc": "US-GA",
    "attempts": 87,
    "activations": 80,
    "qsos": 5876
  },
  {
    "reference": "US-3727",
    "name": "Hart State Park",
    "latitude": 34.3795,
    "longitude": -82.9113,
    "grid": "EM84nj",
    "locationDesc": "US-GA",
    "attempts": 149,
    "activations": 142,
    "qsos": 4855
  },
  {
    "reference": "US-3728",
    "name": "Providence Canyon State Park",
    "latitude": 32.0644,
    "longitude": -84.9219,
    "grid": "EM72mb",
    "locationDesc": "US-GA",
    "attempts": 91,
    "activations": 91,
    "qsos": 4362
  },
  {
    "reference": "US-3729",
    "name": "Rocky Mountain State Recreation Area",
    "latitude": 34.3663,
    "longitude": -85.3033,
    "grid": "EM74ii",
    "locationDesc": "US-GA",
    "attempts": 104,
    "activations": 98,
    "qsos": 3290
  },
  {
    "reference": "US-3730",
    "name": "Altamaha Wildlife Management Area",
    "latitude": 31.3701,
    "longitude": -81.4935,
    "grid": "EM91gi",
    "locationDesc": "US-GA",
    "attempts": 52,
    "activations": 52,
    "qsos": 2114
  },
  {
    "reference": "US-3731",
    "name": "B F Grant Wildlife Management Area",
    "latitude": 33.3925,
    "longitude": -83.4916,
    "grid": "EM83gj",
    "locationDesc": "US-GA",
    "attempts": 53,
    "activations": 53,
    "qsos": 2507
  },
  {
    "reference": "US-3733",
    "name": "Beaverdam Wildlife Management Area",
    "latitude": 32.6929,
    "longitude": -82.9867,
    "grid": "EM82mq",
    "locationDesc": "US-GA",
    "attempts": 36,
    "activations": 36,
    "qsos": 1113
  },
  {
    "reference": "US-3734",
    "name": "Berry College Wildlife Management Area",
    "latitude": 34.3232,
    "longitude": -85.1796,
    "grid": "EM74jh",
    "locationDesc": "US-GA",
    "attempts": 108,
    "activations": 103,
    "qsos": 3406
  },
  {
    "reference": "US-3735",
    "name": "Big Hammock Wildlife Management Area",
    "latitude": 31.8647,
    "longitude": -82.0867,
    "grid": "EM81wu",
    "locationDesc": "US-GA",
    "attempts": 36,
    "activations": 35,
    "qsos": 1650
  },
  {
    "reference": "US-3736",
    "name": "Blanton Creek Wildlife Management Area",
    "latitude": 32.7756,
    "longitude": -85.0858,
    "grid": "EM72ks",
    "locationDesc": "US-GA",
    "attempts": 57,
    "activations": 57,
    "qsos": 1533
  },
  {
    "reference": "US-3737",
    "name": "Bullard Creek Wildlife Management Area",
    "latitude": 31.9426,
    "longitude": -82.5225,
    "grid": "EM81rw",
    "locationDesc": "US-GA",
    "attempts": 38,
    "activations": 37,
    "qsos": 1513
  },
  {
    "reference": "US-3738",
    "name": "Cedar Creek Wildlife Management Area",
    "latitude": 33.2294,
    "longitude": -83.5238,
    "grid": "EM83ff",
    "locationDesc": "US-GA",
    "attempts": 45,
    "activations": 45,
    "qsos": 1553
  },
  {
    "reference": "US-3739",
    "name": "Chickasawhatchee Wildlife Management Area",
    "latitude": 31.5016,
    "longitude": -84.4126,
    "grid": "EM71tm",
    "locationDesc": "US-GA",
    "attempts": 47,
    "activations": 47,
    "qsos": 1630
  },
  {
    "reference": "US-3740",
    "name": "Clayhole Swamp Wildlife Management Area",
    "latitude": 31.3683,
    "longitude": -81.5731,
    "grid": "EM91fi",
    "locationDesc": "US-GA",
    "attempts": 28,
    "activations": 28,
    "qsos": 672
  },
  {
    "reference": "US-3741",
    "name": "Coosawattee Wildlife Management Area",
    "latitude": 34.6319,
    "longitude": -84.7612,
    "grid": "EM74op",
    "locationDesc": "US-GA",
    "attempts": 65,
    "activations": 63,
    "qsos": 1868
  },
  {
    "reference": "US-3742",
    "name": "Crockford-Pigeon Mountain Wildlife Management Area",
    "latitude": 34.7083,
    "longitude": -85.3399,
    "grid": "EM74hq",
    "locationDesc": "US-GA",
    "attempts": 333,
    "activations": 316,
    "qsos": 12633
  },
  {
    "reference": "US-3743",
    "name": "Dawson Forest Wildlife Management Area",
    "latitude": 34.426,
    "longitude": -84.2114,
    "grid": "EM74vk",
    "locationDesc": "US-GA",
    "attempts": 284,
    "activations": 275,
    "qsos": 12892
  },
  {
    "reference": "US-3744",
    "name": "Di-Lane Wildlife Management Area",
    "latitude": 32.9694,
    "longitude": -82.0585,
    "grid": "EM82xx",
    "locationDesc": "US-GA",
    "attempts": 72,
    "activations": 70,
    "qsos": 1595
  },
  {
    "reference": "US-3745",
    "name": "Dixon Bay Wildlife Management Area",
    "latitude": 32.8878,
    "longitude": -81.5522,
    "grid": "EM92fv",
    "locationDesc": "US-GA",
    "attempts": 39,
    "activations": 36,
    "qsos": 881
  },
  {
    "reference": "US-3746",
    "name": "Dixon Memorial Wildlife Management Area",
    "latitude": 31.1164,
    "longitude": -82.2757,
    "grid": "EM81uc",
    "locationDesc": "US-GA",
    "attempts": 334,
    "activations": 316,
    "qsos": 15072
  },
  {
    "reference": "US-3747",
    "name": "Elbert County Wildlife Management Area",
    "latitude": 34.0649,
    "longitude": -82.6542,
    "grid": "EM84qb",
    "locationDesc": "US-GA",
    "attempts": 57,
    "activations": 57,
    "qsos": 1839
  },
  {
    "reference": "US-3748",
    "name": "Elmodel Wildlife Management Area",
    "latitude": 31.3472,
    "longitude": -84.4882,
    "grid": "EM71si",
    "locationDesc": "US-GA",
    "attempts": 34,
    "activations": 34,
    "qsos": 835
  },
  {
    "reference": "US-3749",
    "name": "Flat Tub Wildlife Management Area",
    "latitude": 31.7824,
    "longitude": -82.7956,
    "grid": "EM81os",
    "locationDesc": "US-GA",
    "attempts": 22,
    "activations": 22,
    "qsos": 399
  },
  {
    "reference": "US-3750",
    "name": "Flint River Wildlife Management Area",
    "latitude": 32.1633,
    "longitude": -83.9925,
    "grid": "EM82ad",
    "locationDesc": "US-GA",
    "attempts": 27,
    "activations": 27,
    "qsos": 836
  },
  {
    "reference": "US-3751",
    "name": "Grand Bay Wildlife Management Area",
    "latitude": 30.9205,
    "longitude": -83.1928,
    "grid": "EM80jw",
    "locationDesc": "US-GA",
    "attempts": 163,
    "activations": 163,
    "qsos": 11875
  },
  {
    "reference": "US-3752",
    "name": "Griffin Ridge Wildlife Management Area",
    "latitude": 31.6911,
    "longitude": -81.7877,
    "grid": "EM91cq",
    "locationDesc": "US-GA",
    "attempts": 143,
    "activations": 142,
    "qsos": 5216
  },
  {
    "reference": "US-3753",
    "name": "Hannahatchee Creek Wildlife Management Area",
    "latitude": 32.1092,
    "longitude": -84.7439,
    "grid": "EM72pc",
    "locationDesc": "US-GA",
    "attempts": 29,
    "activations": 29,
    "qsos": 827
  },
  {
    "reference": "US-3754",
    "name": "Hart County Wildlife Management Area",
    "latitude": 34.2995,
    "longitude": -82.8566,
    "grid": "EM84nh",
    "locationDesc": "US-GA",
    "attempts": 47,
    "activations": 47,
    "qsos": 1349
  },
  {
    "reference": "US-3755",
    "name": "Horse Creek Wildlife Management Area",
    "latitude": 31.8317,
    "longitude": -82.868,
    "grid": "EM81nt",
    "locationDesc": "US-GA",
    "attempts": 24,
    "activations": 24,
    "qsos": 644
  },
  {
    "reference": "US-3756",
    "name": "J.L. Lester Wildlife Management Area",
    "latitude": 33.9472,
    "longitude": -85.2053,
    "grid": "EM73jw",
    "locationDesc": "US-GA",
    "attempts": 80,
    "activations": 79,
    "qsos": 3542
  },
  {
    "reference": "US-3757",
    "name": "Joe Kurz Wildlife Management Area",
    "latitude": 33.1142,
    "longitude": -84.5378,
    "grid": "EM73rc",
    "locationDesc": "US-GA",
    "attempts": 119,
    "activations": 119,
    "qsos": 8506
  },
  {
    "reference": "US-3758",
    "name": "John's Mountain Wildlife Management Area",
    "latitude": 34.5791,
    "longitude": -85.0922,
    "grid": "EM74kn",
    "locationDesc": "US-GA",
    "attempts": 227,
    "activations": 219,
    "qsos": 7244
  },
  {
    "reference": "US-3759",
    "name": "Little Satilla Wildlife Management Area",
    "latitude": 31.3516,
    "longitude": -82.0183,
    "grid": "EM81xi",
    "locationDesc": "US-GA",
    "attempts": 29,
    "activations": 28,
    "qsos": 632
  },
  {
    "reference": "US-3760",
    "name": "Mayhaw Wildlife Management Area",
    "latitude": 31.2026,
    "longitude": -84.7973,
    "grid": "EM71oe",
    "locationDesc": "US-GA",
    "attempts": 37,
    "activations": 37,
    "qsos": 1076
  },
  {
    "reference": "US-3761",
    "name": "Oaky Woods Wildlife Management Area",
    "latitude": 32.4848,
    "longitude": -83.5786,
    "grid": "EM82fl",
    "locationDesc": "US-GA",
    "attempts": 141,
    "activations": 138,
    "qsos": 6190
  },
  {
    "reference": "US-3762",
    "name": "Ocmulgee Wildlife Management Area",
    "latitude": 32.339,
    "longitude": -83.481,
    "grid": "EM82gi",
    "locationDesc": "US-GA",
    "attempts": 78,
    "activations": 77,
    "qsos": 4329
  },
  {
    "reference": "US-3763",
    "name": "Oconee Wildlife Management Area",
    "latitude": 33.3896,
    "longitude": -83.1208,
    "grid": "EM83kj",
    "locationDesc": "US-GA",
    "attempts": 51,
    "activations": 47,
    "qsos": 1785
  },
  {
    "reference": "US-3764",
    "name": "Oliver Bridge Wildlife Management Area",
    "latitude": 32.4869,
    "longitude": -81.5706,
    "grid": "EM92fl",
    "locationDesc": "US-GA",
    "attempts": 40,
    "activations": 40,
    "qsos": 1042
  },
  {
    "reference": "US-3765",
    "name": "Ossabaw Island Heritage Wildlife Management Area",
    "latitude": 31.7946,
    "longitude": -81.0983,
    "grid": "EM91kt",
    "locationDesc": "US-GA",
    "attempts": 15,
    "activations": 15,
    "qsos": 828
  },
  {
    "reference": "US-3766",
    "name": "Paulks Pasture Wildlife Management Area",
    "latitude": 31.3198,
    "longitude": -81.5863,
    "grid": "EM91eh",
    "locationDesc": "US-GA",
    "attempts": 42,
    "activations": 42,
    "qsos": 860
  },
  {
    "reference": "US-3767",
    "name": "Penholoway Swamp Wildlife Management Area",
    "latitude": 31.5338,
    "longitude": -81.7163,
    "grid": "EM91dm",
    "locationDesc": "US-GA",
    "attempts": 37,
    "activations": 37,
    "qsos": 983
  },
  {
    "reference": "US-3768",
    "name": "Phinizy Swamp Wildlife Management Area",
    "latitude": 33.4172,
    "longitude": -81.9851,
    "grid": "EM93ak",
    "locationDesc": "US-GA",
    "attempts": 134,
    "activations": 129,
    "qsos": 5455
  },
  {
    "reference": "US-3769",
    "name": "River Bend Wildlife Management Area",
    "latitude": 32.4641,
    "longitude": -82.8218,
    "grid": "EM82ol",
    "locationDesc": "US-GA",
    "attempts": 70,
    "activations": 70,
    "qsos": 1627
  },
  {
    "reference": "US-3770",
    "name": "River Creek - The Rolf and Alexandra Kauka Wildlife Management Area",
    "latitude": 30.8674,
    "longitude": -84.0645,
    "grid": "EM70xu",
    "locationDesc": "US-GA",
    "attempts": 86,
    "activations": 86,
    "qsos": 5147
  },
  {
    "reference": "US-3771",
    "name": "Rogers Wildlife Management Area",
    "latitude": 31.4264,
    "longitude": -81.9342,
    "grid": "EM91ak",
    "locationDesc": "US-GA",
    "attempts": 30,
    "activations": 30,
    "qsos": 619
  },
  {
    "reference": "US-3772",
    "name": "Rum Creek Wildlife Management Area",
    "latitude": 33.0303,
    "longitude": -83.8053,
    "grid": "EM83ca",
    "locationDesc": "US-GA",
    "attempts": 69,
    "activations": 67,
    "qsos": 1551
  },
  {
    "reference": "US-3773",
    "name": "Sansavilla Wildlife Management Area",
    "latitude": 31.4503,
    "longitude": -81.6749,
    "grid": "EM91dk",
    "locationDesc": "US-GA",
    "attempts": 39,
    "activations": 38,
    "qsos": 914
  },
  {
    "reference": "US-3774",
    "name": "Sapelo Island Wildlife Management Area",
    "latitude": 31.4552,
    "longitude": -81.2627,
    "grid": "EM91ik",
    "locationDesc": "US-GA",
    "attempts": 17,
    "activations": 14,
    "qsos": 606
  },
  {
    "reference": "US-3775",
    "name": "Silver Lake Wildlife Management Area",
    "latitude": 30.8208,
    "longitude": -84.7518,
    "grid": "EM70ot",
    "locationDesc": "US-GA",
    "attempts": 40,
    "activations": 38,
    "qsos": 1237
  },
  {
    "reference": "US-3776",
    "name": "Sprewell Bluff Wildlife Management Area",
    "latitude": 32.8546,
    "longitude": -84.4805,
    "grid": "EM72su",
    "locationDesc": "US-GA",
    "attempts": 70,
    "activations": 70,
    "qsos": 3979
  },
  {
    "reference": "US-3777",
    "name": "Wilson Shoals Wildlife Management Area",
    "latitude": 34.4025,
    "longitude": -83.5965,
    "grid": "EM84ej",
    "locationDesc": "US-GA",
    "attempts": 314,
    "activations": 313,
    "qsos": 7382
  },
  {
    "reference": "US-3778",
    "name": "Yuchi Wildlife Management Area",
    "latitude": 33.0992,
    "longitude": -81.7842,
    "grid": "EM93cc",
    "locationDesc": "US-GA",
    "attempts": 110,
    "activations": 102,
    "qsos": 2842
  },
  {
    "reference": "US-3791",
    "name": "Trail of Tears National Historic Trail",
    "latitude": 36.8532,
    "longitude": -87.4701,
    "grid": "EM66gu",
    "locationDesc": "US-AL,US-AR,US-GA,US-IL,US-KY,US-MO,US-NC,US-OK,US-TN",
    "attempts": 6609,
    "activations": 6431,
    "qsos": 272364
  },
  {
    "reference": "US-4473",
    "name": "Chattahoochee-Oconee National Forest",
    "latitude": 34.6648,
    "longitude": -83.9833,
    "grid": "EM84ap",
    "locationDesc": "US-GA",
    "attempts": 2473,
    "activations": 2360,
    "qsos": 109289
  },
  {
    "reference": "US-4556",
    "name": "Appalachian Trail National Scenic Trail",
    "latitude": 34.6267,
    "longitude": -84.1937,
    "grid": "EM74vp",
    "locationDesc": "US-CT,US-GA,US-MA,US-MD,US-ME,US-NC,US-NH,US-NJ,US-NY,US-PA,US-TN,US-VA,US-VT,US-WV",
    "attempts": 5694,
    "activations": 5461,
    "qsos": 200585
  },
  {
    "reference": "US-4586",
    "name": "Big Lazer Creek Wildlife Management Area",
    "latitude": 32.775,
    "longitude": -84.405,
    "grid": "EM72ts",
    "locationDesc": "US-GA",
    "attempts": 60,
    "activations": 57,
    "qsos": 3119
  },
  {
    "reference": "US-4647",
    "name": "Bartram Forest Wildlife Management Area",
    "latitude": 33.0218,
    "longitude": -83.2014,
    "grid": "EM83ja",
    "locationDesc": "US-GA",
    "attempts": 69,
    "activations": 68,
    "qsos": 2703
  },
  {
    "reference": "US-4648",
    "name": "Bartram Educational State Forest",
    "latitude": 33,
    "longitude": -83.216,
    "grid": "EM83ja",
    "locationDesc": "US-GA",
    "attempts": 67,
    "activations": 67,
    "qsos": 2618
  },
  {
    "reference": "US-4649",
    "name": "Hitchiti State Forest",
    "latitude": 33.05,
    "longitude": -83.7146,
    "grid": "EM83db",
    "locationDesc": "US-GA",
    "attempts": 67,
    "activations": 67,
    "qsos": 2148
  },
  {
    "reference": "US-4650",
    "name": "Dawson State Forest",
    "latitude": 34.414,
    "longitude": -84.208,
    "grid": "EM74vj",
    "locationDesc": "US-GA",
    "attempts": 274,
    "activations": 268,
    "qsos": 13597
  },
  {
    "reference": "US-4651",
    "name": "Dixon Memorial State Forest",
    "latitude": 31.0924,
    "longitude": -82.289,
    "grid": "EM81uc",
    "locationDesc": "US-GA",
    "attempts": 329,
    "activations": 311,
    "qsos": 14710
  },
  {
    "reference": "US-4653",
    "name": "Paulding Forest Wildlife Management Area",
    "latitude": 33.991,
    "longitude": -84.9594,
    "grid": "EM73mx",
    "locationDesc": "US-GA",
    "attempts": 104,
    "activations": 101,
    "qsos": 4195
  },
  {
    "reference": "US-4654",
    "name": "Spirit Creek Forest Wildlife Management Area",
    "latitude": 33.3469,
    "longitude": -82.0223,
    "grid": "EM83xi",
    "locationDesc": "US-GA",
    "attempts": 67,
    "activations": 65,
    "qsos": 2504
  },
  {
    "reference": "US-7135",
    "name": "Blue Ridge Wildlife Management Area",
    "latitude": 34.6605,
    "longitude": -84.1791,
    "grid": "EM74vp",
    "locationDesc": "US-GA",
    "attempts": 87,
    "activations": 80,
    "qsos": 3048
  },
  {
    "reference": "US-7136",
    "name": "Tuckahoe Wildlife Management Area",
    "latitude": 32.82,
    "longitude": -81.4834,
    "grid": "EM92gt",
    "locationDesc": "US-GA",
    "attempts": 36,
    "activations": 35,
    "qsos": 858
  },
  {
    "reference": "US-7137",
    "name": "Cooper's Creek Wildlife Management Area",
    "latitude": 34.7705,
    "longitude": -84.0681,
    "grid": "EM74xs",
    "locationDesc": "US-GA",
    "attempts": 118,
    "activations": 109,
    "qsos": 2859
  },
  {
    "reference": "US-7138",
    "name": "Chestatee Wildlife Management Area",
    "latitude": 34.7147,
    "longitude": -83.9195,
    "grid": "EM84ar",
    "locationDesc": "US-GA",
    "attempts": 407,
    "activations": 401,
    "qsos": 8816
  },
  {
    "reference": "US-7139",
    "name": "Arabia Mountain National Heritage Area",
    "latitude": 33.6724,
    "longitude": -84.1159,
    "grid": "EM73wq",
    "locationDesc": "US-GA",
    "attempts": 290,
    "activations": 278,
    "qsos": 12918
  },
  {
    "reference": "US-7140",
    "name": "Charlie Elliot Wildlife Management Area",
    "latitude": 33.4625,
    "longitude": -83.7367,
    "grid": "EM83dl",
    "locationDesc": "US-GA",
    "attempts": 240,
    "activations": 236,
    "qsos": 15500
  },
  {
    "reference": "US-7141",
    "name": "Clybel Wildlife Management Area",
    "latitude": 33.4691,
    "longitude": -83.7287,
    "grid": "EM83dl",
    "locationDesc": "US-GA",
    "attempts": 232,
    "activations": 231,
    "qsos": 15280
  },
  {
    "reference": "US-7142",
    "name": "Redlands Wildlife Management Area",
    "latitude": 33.6805,
    "longitude": -83.2726,
    "grid": "EM83iq",
    "locationDesc": "US-GA",
    "attempts": 212,
    "activations": 209,
    "qsos": 9599
  },
  {
    "reference": "US-7446",
    "name": "Cohutta Wildlife Management Area",
    "latitude": 34.8961,
    "longitude": -84.6172,
    "grid": "EM74qv",
    "locationDesc": "US-GA",
    "attempts": 115,
    "activations": 108,
    "qsos": 3624
  },
  {
    "reference": "US-7447",
    "name": "Chattahoochee Wildlife Management Area",
    "latitude": 34.7416,
    "longitude": -83.7743,
    "grid": "EM84cr",
    "locationDesc": "US-GA",
    "attempts": 184,
    "activations": 176,
    "qsos": 6351
  },
  {
    "reference": "US-7448",
    "name": "Lula Bridge Wildlife Management Area",
    "latitude": 34.4146,
    "longitude": -83.7084,
    "grid": "EM84dj",
    "locationDesc": "US-GA",
    "attempts": 378,
    "activations": 374,
    "qsos": 8335
  },
  {
    "reference": "US-7449",
    "name": "Buck Shoals Wildlife Management Area",
    "latitude": 34.5596,
    "longitude": -83.6348,
    "grid": "EM84en",
    "locationDesc": "US-GA",
    "attempts": 82,
    "activations": 81,
    "qsos": 2852
  },
  {
    "reference": "US-7450",
    "name": "Warwoman Wildlife Management Area",
    "latitude": 34.8892,
    "longitude": -83.3406,
    "grid": "EM84hv",
    "locationDesc": "US-GA",
    "attempts": 107,
    "activations": 98,
    "qsos": 2742
  },
  {
    "reference": "US-7451",
    "name": "Swallow Creek Wildlife Management Area",
    "latitude": 34.8161,
    "longitude": -83.7269,
    "grid": "EM84dt",
    "locationDesc": "US-GA",
    "attempts": 127,
    "activations": 123,
    "qsos": 2957
  },
  {
    "reference": "US-7452",
    "name": "Rich Mountain Wildlife Management Area",
    "latitude": 34.7809,
    "longitude": -84.3121,
    "grid": "EM74us",
    "locationDesc": "US-GA",
    "attempts": 86,
    "activations": 82,
    "qsos": 2950
  },
  {
    "reference": "US-7453",
    "name": "Allatoona Wildlife Management Area",
    "latitude": 34.2171,
    "longitude": -84.6893,
    "grid": "EM74pf",
    "locationDesc": "US-GA",
    "attempts": 194,
    "activations": 186,
    "qsos": 7774
  },
  {
    "reference": "US-7454",
    "name": "McGraw Ford Wildlife Management Area",
    "latitude": 34.3231,
    "longitude": -84.349,
    "grid": "EM74th",
    "locationDesc": "US-GA",
    "attempts": 190,
    "activations": 180,
    "qsos": 6229
  },
  {
    "reference": "US-7455",
    "name": "Lake Russell Wildlife Management Area",
    "latitude": 34.5471,
    "longitude": -83.4144,
    "grid": "EM84hn",
    "locationDesc": "US-GA",
    "attempts": 110,
    "activations": 103,
    "qsos": 3047
  },
  {
    "reference": "US-7456",
    "name": "Dahlonega Gold Museum State Historic Site",
    "latitude": 34.5327,
    "longitude": -83.9849,
    "grid": "EM84am",
    "locationDesc": "US-GA",
    "attempts": 818,
    "activations": 809,
    "qsos": 47568
  },
  {
    "reference": "US-7457",
    "name": "Chief Vann House State Historic Site",
    "latitude": 34.7643,
    "longitude": -84.8222,
    "grid": "EM74os",
    "locationDesc": "US-GA",
    "attempts": 90,
    "activations": 86,
    "qsos": 2170
  },
  {
    "reference": "US-7458",
    "name": "Travelers Rest State Historic Site",
    "latitude": 34.609,
    "longitude": -83.2389,
    "grid": "EM84jo",
    "locationDesc": "US-GA",
    "attempts": 60,
    "activations": 60,
    "qsos": 1267
  },
  {
    "reference": "US-7459",
    "name": "Lake Nottely Dam Recreation Park",
    "latitude": 34.9559,
    "longitude": -84.0845,
    "grid": "EM74ww",
    "locationDesc": "US-GA",
    "attempts": 543,
    "activations": 538,
    "qsos": 37762
  },
  {
    "reference": "US-7460",
    "name": "Lake Blue Ridge Dam Recreation Park",
    "latitude": 34.8847,
    "longitude": -84.2818,
    "grid": "EM74uv",
    "locationDesc": "US-GA",
    "attempts": 177,
    "activations": 175,
    "qsos": 9684
  },
  {
    "reference": "US-7461",
    "name": "Ocmulgee State Fishing Lake",
    "latitude": 32.3839,
    "longitude": -83.4883,
    "grid": "EM82gj",
    "locationDesc": "US-GA",
    "attempts": 76,
    "activations": 75,
    "qsos": 4215
  },
  {
    "reference": "US-7462",
    "name": "Big Lazer Creek State Fishing Lake",
    "latitude": 32.7753,
    "longitude": -84.407,
    "grid": "EM72ts",
    "locationDesc": "US-GA",
    "attempts": 56,
    "activations": 55,
    "qsos": 3267
  },
  {
    "reference": "US-7463",
    "name": "Dodge County State Fishing Lake",
    "latitude": 32.1586,
    "longitude": -83.1329,
    "grid": "EM82kd",
    "locationDesc": "US-GA",
    "attempts": 51,
    "activations": 51,
    "qsos": 1347
  },
  {
    "reference": "US-7464",
    "name": "Evans County State Fishing Lake",
    "latitude": 32.1284,
    "longitude": -81.7938,
    "grid": "EM92cd",
    "locationDesc": "US-GA",
    "attempts": 438,
    "activations": 427,
    "qsos": 19590
  },
  {
    "reference": "US-7465",
    "name": "Flat Creek State Fishing Lake",
    "latitude": 32.4079,
    "longitude": -83.7769,
    "grid": "EM82cj",
    "locationDesc": "US-GA",
    "attempts": 462,
    "activations": 438,
    "qsos": 22489
  },
  {
    "reference": "US-7466",
    "name": "Hugh M. Gillis State Fishing Lake",
    "latitude": 32.5713,
    "longitude": -82.718,
    "grid": "EM82pn",
    "locationDesc": "US-GA",
    "attempts": 47,
    "activations": 45,
    "qsos": 1377
  },
  {
    "reference": "US-7467",
    "name": "Marben State Fishing Lake",
    "latitude": 33.4435,
    "longitude": -83.7367,
    "grid": "EM83dk",
    "locationDesc": "US-GA",
    "attempts": 227,
    "activations": 225,
    "qsos": 15238
  },
  {
    "reference": "US-7468",
    "name": "McDuffie State Fishing Lake",
    "latitude": 33.3784,
    "longitude": -82.4235,
    "grid": "EM83sj",
    "locationDesc": "US-GA",
    "attempts": 61,
    "activations": 59,
    "qsos": 2457
  },
  {
    "reference": "US-7469",
    "name": "Paradise State Fishing Lake",
    "latitude": 31.401,
    "longitude": -83.3691,
    "grid": "EM81hj",
    "locationDesc": "US-GA",
    "attempts": 102,
    "activations": 98,
    "qsos": 3108
  },
  {
    "reference": "US-7470",
    "name": "Silver Lake State Fishing Lake",
    "latitude": 30.8205,
    "longitude": -84.7516,
    "grid": "EM70ot",
    "locationDesc": "US-GA",
    "attempts": 44,
    "activations": 43,
    "qsos": 1402
  },
  {
    "reference": "US-7471",
    "name": "Allatoona Pass Battlefield State Historic Site",
    "latitude": 34.1138,
    "longitude": -84.715,
    "grid": "EM74pc",
    "locationDesc": "US-GA",
    "attempts": 246,
    "activations": 231,
    "qsos": 8481
  },
  {
    "reference": "US-7472",
    "name": "Griswoldville Battlefield State Historic Site",
    "latitude": 32.8693,
    "longitude": -83.4599,
    "grid": "EM82gu",
    "locationDesc": "US-GA",
    "attempts": 84,
    "activations": 81,
    "qsos": 2815
  },
  {
    "reference": "US-7473",
    "name": "DeSoto Falls National Recreation Area",
    "latitude": 34.7055,
    "longitude": -83.9149,
    "grid": "EM84bq",
    "locationDesc": "US-GA",
    "attempts": 112,
    "activations": 109,
    "qsos": 2722
  },
  {
    "reference": "US-7838",
    "name": "Gaither Wildlife Management Area",
    "latitude": 33.462,
    "longitude": -83.797,
    "grid": "EM83cl",
    "locationDesc": "US-GA",
    "attempts": 72,
    "activations": 71,
    "qsos": 2987
  },
  {
    "reference": "US-7852",
    "name": "Richmond Hill Wildlife Management Area",
    "latitude": 31.797,
    "longitude": -81.2216,
    "grid": "EM91jt",
    "locationDesc": "US-GA",
    "attempts": 89,
    "activations": 87,
    "qsos": 4346
  },
  {
    "reference": "US-7858",
    "name": "Dames Ferry Campground State Park",
    "latitude": 33.0442,
    "longitude": -83.7577,
    "grid": "EM83cb",
    "locationDesc": "US-GA",
    "attempts": 127,
    "activations": 118,
    "qsos": 4161
  },
  {
    "reference": "US-7860",
    "name": "Buford Trout Hatchery State Fish Hatchery",
    "latitude": 34.1389,
    "longitude": -84.0923,
    "grid": "EM74wd",
    "locationDesc": "US-GA",
    "attempts": 392,
    "activations": 383,
    "qsos": 9056
  },
  {
    "reference": "US-7861",
    "name": "Suwannee River Eco-Lodge State Park",
    "latitude": 30.6968,
    "longitude": -82.5607,
    "grid": "EM80rq",
    "locationDesc": "US-GA",
    "attempts": 32,
    "activations": 31,
    "qsos": 1090
  },
  {
    "reference": "US-7881",
    "name": "Alapaha River Wildlife Management Area",
    "latitude": 31.539,
    "longitude": -83.3887,
    "grid": "EM81hm",
    "locationDesc": "US-GA",
    "attempts": 69,
    "activations": 65,
    "qsos": 2249
  },
  {
    "reference": "US-7882",
    "name": "Doerun Pitcherplant Bog Wildlife Management Area",
    "latitude": 31.2863,
    "longitude": -83.8879,
    "grid": "EM81bg",
    "locationDesc": "US-GA",
    "attempts": 892,
    "activations": 890,
    "qsos": 33395
  },
  {
    "reference": "US-7883",
    "name": "West Point Wildlife Management Area",
    "latitude": 33.1605,
    "longitude": -85.0665,
    "grid": "EM73ld",
    "locationDesc": "US-GA",
    "attempts": 83,
    "activations": 82,
    "qsos": 3501
  },
  {
    "reference": "US-7893",
    "name": "Augusta Canal National Heritage Area",
    "latitude": 33.512,
    "longitude": -82.0029,
    "grid": "EM83xm",
    "locationDesc": "US-GA",
    "attempts": 272,
    "activations": 258,
    "qsos": 12397
  },
  {
    "reference": "US-7895",
    "name": "Sheffield Wildlife Management Area",
    "latitude": 34.0242,
    "longitude": -84.9062,
    "grid": "EM74na",
    "locationDesc": "US-GA",
    "attempts": 116,
    "activations": 115,
    "qsos": 5511
  },
  {
    "reference": "US-7896",
    "name": "Standing Boy Creek State Park",
    "latitude": 32.5821,
    "longitude": -85.0358,
    "grid": "EM72ln",
    "locationDesc": "US-GA",
    "attempts": 89,
    "activations": 85,
    "qsos": 3047
  },
  {
    "reference": "US-7897",
    "name": "Arrowhead Wildlife Management Area",
    "latitude": 34.4398,
    "longitude": -85.1512,
    "grid": "EM74kk",
    "locationDesc": "US-GA",
    "attempts": 97,
    "activations": 97,
    "qsos": 4139
  },
  {
    "reference": "US-7898",
    "name": "Conasauga River Wildlife Management Area",
    "latitude": 34.8277,
    "longitude": -84.8534,
    "grid": "EM74nt",
    "locationDesc": "US-GA",
    "attempts": 69,
    "activations": 69,
    "qsos": 2622
  },
  {
    "reference": "US-7899",
    "name": "Carter's Lake Wildlife Management Area",
    "latitude": 34.6141,
    "longitude": -84.6796,
    "grid": "EM74po",
    "locationDesc": "US-GA",
    "attempts": 226,
    "activations": 212,
    "qsos": 8987
  },
  {
    "reference": "US-7900",
    "name": "Echeconnee Creek Wildlife Management Area",
    "latitude": 32.6698,
    "longitude": -83.6165,
    "grid": "EM82eq",
    "locationDesc": "US-GA",
    "attempts": 123,
    "activations": 114,
    "qsos": 4225
  },
  {
    "reference": "US-7901",
    "name": "Ohoopee Dunes Wildlife Management Area",
    "latitude": 32.5708,
    "longitude": -82.4332,
    "grid": "EM82sn",
    "locationDesc": "US-GA",
    "attempts": 37,
    "activations": 37,
    "qsos": 945
  },
  {
    "reference": "US-7902",
    "name": "Walton Wildlife Management Area",
    "latitude": 33.625,
    "longitude": -83.6781,
    "grid": "EM83dp",
    "locationDesc": "US-GA",
    "attempts": 135,
    "activations": 134,
    "qsos": 4559
  },
  {
    "reference": "US-7903",
    "name": "Zahnd Wildlife Management Area",
    "latitude": 34.655,
    "longitude": -85.4699,
    "grid": "EM74gp",
    "locationDesc": "US-GA",
    "attempts": 82,
    "activations": 81,
    "qsos": 2632
  },
  {
    "reference": "US-7904",
    "name": "Broad River Wildlife Management Area",
    "latitude": 34.1867,
    "longitude": -83.1438,
    "grid": "EM84ke",
    "locationDesc": "US-GA",
    "attempts": 76,
    "activations": 75,
    "qsos": 3464
  },
  {
    "reference": "US-7905",
    "name": "Canoochee Sandhills Wildlife Management Area",
    "latitude": 32.1899,
    "longitude": -81.7669,
    "grid": "EM92ce",
    "locationDesc": "US-GA",
    "attempts": 81,
    "activations": 80,
    "qsos": 2336
  },
  {
    "reference": "US-7906",
    "name": "Chattahoochee Fall Line Almo Tract Wildlife Management Area",
    "latitude": 32.5441,
    "longitude": -84.5269,
    "grid": "EM72rn",
    "locationDesc": "US-GA",
    "attempts": 41,
    "activations": 40,
    "qsos": 1348
  },
  {
    "reference": "US-7907",
    "name": "Clarks Hill Wildlife Management Area",
    "latitude": 33.6277,
    "longitude": -82.5315,
    "grid": "EM83rp",
    "locationDesc": "US-GA",
    "attempts": 56,
    "activations": 55,
    "qsos": 2237
  },
  {
    "reference": "US-7908",
    "name": "Fishing Creek Wildlife Management Area",
    "latitude": 33.8569,
    "longitude": -82.5899,
    "grid": "EM83qu",
    "locationDesc": "US-GA",
    "attempts": 34,
    "activations": 33,
    "qsos": 1375
  },
  {
    "reference": "US-7909",
    "name": "Germany Creek Wildlife Management Area",
    "latitude": 33.6113,
    "longitude": -82.464,
    "grid": "EM83so",
    "locationDesc": "US-GA",
    "attempts": 43,
    "activations": 42,
    "qsos": 1724
  },
  {
    "reference": "US-7910",
    "name": "Keg Creek Wildlife Management Area",
    "latitude": 33.6346,
    "longitude": -82.2991,
    "grid": "EM83up",
    "locationDesc": "US-GA",
    "attempts": 98,
    "activations": 92,
    "qsos": 4708
  },
  {
    "reference": "US-7911",
    "name": "Lake Walter F. George Wildlife Management Area",
    "latitude": 31.8451,
    "longitude": -85.1142,
    "grid": "EM71ku",
    "locationDesc": "US-GA",
    "attempts": 31,
    "activations": 31,
    "qsos": 879
  },
  {
    "reference": "US-7912",
    "name": "Montezuma Bluffs Wildlife Management Area",
    "latitude": 32.337,
    "longitude": -84.0286,
    "grid": "EM72xi",
    "locationDesc": "US-GA",
    "attempts": 28,
    "activations": 28,
    "qsos": 751
  },
  {
    "reference": "US-7913",
    "name": "Otting Wildlife Management Area",
    "latitude": 34.534,
    "longitude": -85.4683,
    "grid": "EM74gm",
    "locationDesc": "US-GA",
    "attempts": 82,
    "activations": 81,
    "qsos": 2641
  },
  {
    "reference": "US-7914",
    "name": "Sandhills East Wildlife Management Area",
    "latitude": 32.5683,
    "longitude": -84.2744,
    "grid": "EM72un",
    "locationDesc": "US-GA",
    "attempts": 44,
    "activations": 44,
    "qsos": 1406
  },
  {
    "reference": "US-9758",
    "name": "Chattooga National Wild and Scenic River",
    "latitude": 34.9402,
    "longitude": -83.1928,
    "grid": "EM84jw",
    "locationDesc": "US-GA,US-NC,US-SC",
    "attempts": 106,
    "activations": 103,
    "qsos": 4278
  },
  {
    "reference": "US-9763",
    "name": "Albany Nursery Wildlife Management Area",
    "latitude": 31.5921,
    "longitude": -84.3466,
    "grid": "EM71to",
    "locationDesc": "US-GA",
    "attempts": 49,
    "activations": 48,
    "qsos": 1580
  },
  {
    "reference": "US-9765",
    "name": "Alexander Wildlife Management Area",
    "latitude": 33.0086,
    "longitude": -81.8983,
    "grid": "EM93ba",
    "locationDesc": "US-GA",
    "attempts": 26,
    "activations": 26,
    "qsos": 727
  },
  {
    "reference": "US-9767",
    "name": "Alligator Creek Wildlife Management Area",
    "latitude": 31.9514,
    "longitude": -82.6551,
    "grid": "EM81qw",
    "locationDesc": "US-GA",
    "attempts": 25,
    "activations": 25,
    "qsos": 662
  },
  {
    "reference": "US-9770",
    "name": "Altama Plantation Wildlife Management Area",
    "latitude": 31.3031,
    "longitude": -81.4835,
    "grid": "EM91gh",
    "locationDesc": "US-GA",
    "attempts": 72,
    "activations": 72,
    "qsos": 1606
  },
  {
    "reference": "US-9772",
    "name": "Ceylon Wildlife Management Area",
    "latitude": 30.944,
    "longitude": -81.6712,
    "grid": "EM90dw",
    "locationDesc": "US-GA",
    "attempts": 74,
    "activations": 71,
    "qsos": 2608
  },
  {
    "reference": "US-9774",
    "name": "Lower Broad River Wildlife Management Area",
    "latitude": 33.9985,
    "longitude": -82.6597,
    "grid": "EM83qx",
    "locationDesc": "US-GA",
    "attempts": 43,
    "activations": 42,
    "qsos": 1494
  },
  {
    "reference": "US-9776",
    "name": "Mead Farm Wildlife Management Area",
    "latitude": 33.1354,
    "longitude": -81.8955,
    "grid": "EM93bd",
    "locationDesc": "US-GA",
    "attempts": 47,
    "activations": 44,
    "qsos": 943
  },
  {
    "reference": "US-9777",
    "name": "Moody Forest Wildlife Management Area",
    "latitude": 31.9067,
    "longitude": -82.3119,
    "grid": "EM81uv",
    "locationDesc": "US-GA",
    "attempts": 17,
    "activations": 16,
    "qsos": 405
  },
  {
    "reference": "US-9779",
    "name": "Soap Creek Wildlife Management Area",
    "latitude": 33.8282,
    "longitude": -82.4707,
    "grid": "EM83st",
    "locationDesc": "US-GA",
    "attempts": 21,
    "activations": 20,
    "qsos": 1447
  },
  {
    "reference": "US-9780",
    "name": "Townsend Wildlife Management Area",
    "latitude": 31.6176,
    "longitude": -81.6663,
    "grid": "EM91eo",
    "locationDesc": "US-GA",
    "attempts": 33,
    "activations": 29,
    "qsos": 873
  },
  {
    "reference": "US-9782",
    "name": "Big Dukes Pond Wildlife Management Area",
    "latitude": 32.8705,
    "longitude": -82.0357,
    "grid": "EM82xu",
    "locationDesc": "US-GA",
    "attempts": 27,
    "activations": 26,
    "qsos": 717
  },
  {
    "reference": "US-9784",
    "name": "Hiltonia Wildlife Management Area",
    "latitude": 32.8909,
    "longitude": -81.7151,
    "grid": "EM92dv",
    "locationDesc": "US-GA",
    "attempts": 30,
    "activations": 29,
    "qsos": 1102
  },
  {
    "reference": "US-9786",
    "name": "Lake Seminole Wildlife Management Area",
    "latitude": 30.847,
    "longitude": -84.662,
    "grid": "EM70qu",
    "locationDesc": "US-GA",
    "attempts": 36,
    "activations": 36,
    "qsos": 1255
  },
  {
    "reference": "US-9788",
    "name": "Lanahassee Creek Wildlife Management Area",
    "latitude": 32.0441,
    "longitude": -84.4882,
    "grid": "EM72sb",
    "locationDesc": "US-GA",
    "attempts": 21,
    "activations": 21,
    "qsos": 623
  },
  {
    "reference": "US-9791",
    "name": "Morgan Lake Wildlife Management Area",
    "latitude": 31.6691,
    "longitude": -81.8147,
    "grid": "EM91cq",
    "locationDesc": "US-GA",
    "attempts": 22,
    "activations": 21,
    "qsos": 531
  },
  {
    "reference": "US-9793",
    "name": "Ball's Ferry Property Wildlife Management Area",
    "latitude": 32.783,
    "longitude": -82.9647,
    "grid": "EM82ms",
    "locationDesc": "US-GA",
    "attempts": 35,
    "activations": 35,
    "qsos": 1302
  },
  {
    "reference": "US-9795",
    "name": "Sandhills West Wildlife Management Area",
    "latitude": 32.5703,
    "longitude": -84.4072,
    "grid": "EM72tn",
    "locationDesc": "US-GA",
    "attempts": 25,
    "activations": 25,
    "qsos": 813
  },
  {
    "reference": "US-9797",
    "name": "Chattahoochee Fall Line Hilliard Tract Wildlife Management Area",
    "latitude": 32.4098,
    "longitude": -84.5838,
    "grid": "EM72qj",
    "locationDesc": "US-GA",
    "attempts": 21,
    "activations": 21,
    "qsos": 742
  },
  {
    "reference": "US-9798",
    "name": "Centennial Olympic State Park",
    "latitude": 33.7605,
    "longitude": -84.3931,
    "grid": "EM73ts",
    "locationDesc": "US-GA",
    "attempts": 48,
    "activations": 47,
    "qsos": 1071
  },
  {
    "reference": "US-9799",
    "name": "Stone Mountain (GA) State Park",
    "latitude": 33.8056,
    "longitude": -84.1458,
    "grid": "EM73wt",
    "locationDesc": "US-GA",
    "attempts": 399,
    "activations": 369,
    "qsos": 12200
  },
  {
    "reference": "US-10397",
    "name": "Southern Nantahala Wilderness Area",
    "latitude": 35.0395,
    "longitude": -83.5528,
    "grid": "EM85fa",
    "locationDesc": "US-GA,US-NC",
    "attempts": 60,
    "activations": 57,
    "qsos": 2059
  },
  {
    "reference": "US-12416",
    "name": "Little River (GA) Wildlife Management Area",
    "latitude": 33.3145,
    "longitude": -83.4584,
    "grid": "EM83gh",
    "locationDesc": "US-GA",
    "attempts": 17,
    "activations": 16,
    "qsos": 583
  },
  {
    "reference": "US-12417",
    "name": "Rich Mountain Cartecay Tract Wildlife Management Area",
    "latitude": 34.6466,
    "longitude": -84.4384,
    "grid": "EM74sp",
    "locationDesc": "US-GA",
    "attempts": 61,
    "activations": 60,
    "qsos": 2399
  },
  {
    "reference": "US-12418",
    "name": "Tallulah Gorge Wildlife Management Area",
    "latitude": 34.7241,
    "longitude": -83.3809,
    "grid": "EM84hr",
    "locationDesc": "US-GA",
    "attempts": 40,
    "activations": 39,
    "qsos": 1145
  },
  {
    "reference": "US-12419",
    "name": "Tallapoosa River Wildlife Management Area",
    "latitude": 33.8952,
    "longitude": -85.1204,
    "grid": "EM73kv",
    "locationDesc": "US-GA",
    "attempts": 22,
    "activations": 21,
    "qsos": 584
  },
  {
    "reference": "US-12420",
    "name": "Treat Mountain Wildlife Management Area",
    "latitude": 33.902,
    "longitude": -85.3523,
    "grid": "EM73hv",
    "locationDesc": "US-GA",
    "attempts": 24,
    "activations": 22,
    "qsos": 671
  },
  {
    "reference": "US-12421",
    "name": "Cochrans Creek Wildlife Management Area",
    "latitude": 34.5376,
    "longitude": -84.2097,
    "grid": "EM74vm",
    "locationDesc": "US-GA",
    "attempts": 38,
    "activations": 38,
    "qsos": 1071
  },
  {
    "reference": "US-12768",
    "name": "Bowens Mill State Fish Hatchery",
    "latitude": 31.848,
    "longitude": -83.2111,
    "grid": "EM81ju",
    "locationDesc": "US-GA",
    "attempts": 11,
    "activations": 11,
    "qsos": 398
  },
  {
    "reference": "US-12769",
    "name": "Cordele State Fish Hatchery",
    "latitude": 31.9685,
    "longitude": -83.8243,
    "grid": "EM81cx",
    "locationDesc": "US-GA",
    "attempts": 10,
    "activations": 10,
    "qsos": 346
  },
  {
    "reference": "US-12770",
    "name": "Richmond Hill State Fish Hatchery",
    "latitude": 31.9542,
    "longitude": -81.3168,
    "grid": "EM91iw",
    "locationDesc": "US-GA",
    "attempts": 50,
    "activations": 50,
    "qsos": 2650
  },
  {
    "reference": "US-12771",
    "name": "Summerville State Fish Hatchery",
    "latitude": 34.4747,
    "longitude": -85.409,
    "grid": "EM74hl",
    "locationDesc": "US-GA",
    "attempts": 26,
    "activations": 26,
    "qsos": 916
  },
  {
    "reference": "US-12772",
    "name": "Georgia National Fairgrounds State Recreation Area",
    "latitude": 32.441,
    "longitude": -83.75,
    "grid": "EM82dk",
    "locationDesc": "US-GA",
    "attempts": 83,
    "activations": 80,
    "qsos": 3245
  },
  {
    "reference": "US-12773",
    "name": "Warm Springs National Fish Hatchery",
    "latitude": 32.8853,
    "longitude": -84.6742,
    "grid": "EM72pv",
    "locationDesc": "US-GA",
    "attempts": 23,
    "activations": 23,
    "qsos": 1056
  }
]
