[
  {
    "reference": "US-0180",
    "name": "Twin Lights State Historic Site",
    "latitude": 40.3962,
    "longitude": -73.986,
    "grid": "FN30aj",
    "locationDesc": "US-NJ",
    "attempts": 121,
    "activations": 114,
    "qsos": 3951
  },
  {
    "reference": "US-0452",
    "name": "Cape May National Wildlife Refuge",
    "latitude": 39.0998,
    "longitude": -74.8796,
    "grid": "FM29nc",
    "locationDesc": "US-NJ",
    "attempts": 76,
    "activations": 70,
    "qsos": 1808
  },
  {
    "reference": "US-0453",
    "name": "Edwin B. Forsythe National Wildlife Refuge",
    "latitude": 39.4647,
    "longitude": -74.4498,
    "grid": "FM29sl",
    "locationDesc": "US-NJ",
    "attempts": 413,
    "activations": 403,
    "qsos": 12219
  },
  {
    "reference": "US-0454",
    "name": "Great Swamp National Wildlife Refuge",
    "latitude": 40.7136,
    "longitude": -74.5133,
    "grid": "FN20rr",
    "locationDesc": "US-NJ",
    "attempts": 261,
    "activations": 256,
    "qsos": 8858
  },
  {
    "reference": "US-0455",
    "name": "Supawna Meadows National Wildlife Refuge",
    "latitude": 39.6169,
    "longitude": -75.5343,
    "grid": "FM29fo",
    "locationDesc": "US-NJ",
    "attempts": 67,
    "activations": 65,
    "qsos": 2047
  },
  {
    "reference": "US-0456",
    "name": "Wallkill River National Wildlife Refuge",
    "latitude": 41.2008,
    "longitude": -74.5642,
    "grid": "FN21re",
    "locationDesc": "US-NJ,US-NY",
    "attempts": 230,
    "activations": 218,
    "qsos": 7614
  },
  {
    "reference": "US-0677",
    "name": "Great Egg Harbor National Wild and Scenic River",
    "latitude": 39.4488,
    "longitude": -74.7269,
    "grid": "FM29pk",
    "locationDesc": "US-NJ",
    "attempts": 78,
    "activations": 76,
    "qsos": 3117
  },
  {
    "reference": "US-0680",
    "name": "Gateway National Recreation Area",
    "latitude": 40.6043,
    "longitude": -74.058,
    "grid": "FN20xo",
    "locationDesc": "US-NJ,US-NY",
    "attempts": 1391,
    "activations": 1365,
    "qsos": 113085
  },
  {
    "reference": "US-0684",
    "name": "Lower Delaware National Wild and Scenic River",
    "latitude": 40.297,
    "longitude": -74.872,
    "grid": "FN20nh",
    "locationDesc": "US-NJ,US-PA",
    "attempts": 442,
    "activations": 424,
    "qsos": 12597
  },
  {
    "reference": "US-0746",
    "name": "Morristown National Historical Park",
    "latitude": 40.7636,
    "longitude": -74.5428,
    "grid": "FN20rs",
    "locationDesc": "US-NJ",
    "attempts": 398,
    "activations": 384,
    "qsos": 12910
  },
  {
    "reference": "US-0751",
    "name": "Paterson Great Falls National Historical Park",
    "latitude": 40.9167,
    "longitude": -74.1796,
    "grid": "FN20vw",
    "locationDesc": "US-NJ",
    "attempts": 280,
    "activations": 271,
    "qsos": 9809
  },
  {
    "reference": "US-0759",
    "name": "Thomas Edison National Historical Park",
    "latitude": 40.784,
    "longitude": -74.2393,
    "grid": "FN20vs",
    "locationDesc": "US-NJ",
    "attempts": 76,
    "activations": 75,
    "qsos": 3732
  },
  {
    "reference": "US-0886",
    "name": "Maurice River National Wild and Scenic River",
    "latitude": 39.2869,
    "longitude": -74.9865,
    "grid": "FM29mg",
    "locationDesc": "US-NJ",
    "attempts": 74,
    "activations": 68,
    "qsos": 3176
  },
  {
    "reference": "US-0888",
    "name": "Musconetcong River National Wild and Scenic River",
    "latitude": 40.7122,
    "longitude": -74.9677,
    "grid": "FN20mr",
    "locationDesc": "US-NJ",
    "attempts": 278,
    "activations": 262,
    "qsos": 7733
  },
  {
    "reference": "US-1607",
    "name": "Allaire State Park",
    "latitude": 40.1602,
    "longitude": -74.1324,
    "grid": "FN20wd",
    "locationDesc": "US-NJ",
    "attempts": 212,
    "activations": 205,
    "qsos": 6671
  },
  {
    "reference": "US-1608",
    "name": "Allamuchy Mountain State Park",
    "latitude": 40.9305,
    "longitude": -74.749,
    "grid": "FN20pw",
    "locationDesc": "US-NJ",
    "attempts": 214,
    "activations": 210,
    "qsos": 6111
  },
  {
    "reference": "US-1609",
    "name": "Barnegat Lighthouse State Park",
    "latitude": 39.7638,
    "longitude": -74.1057,
    "grid": "FM29ws",
    "locationDesc": "US-NJ",
    "attempts": 234,
    "activations": 230,
    "qsos": 6483
  },
  {
    "reference": "US-1610",
    "name": "Cape May Point State Park",
    "latitude": 38.936,
    "longitude": -74.9566,
    "grid": "FM28mw",
    "locationDesc": "US-NJ",
    "attempts": 245,
    "activations": 230,
    "qsos": 6981
  },
  {
    "reference": "US-1611",
    "name": "Cheesequake State Park",
    "latitude": 40.4377,
    "longitude": -74.2666,
    "grid": "FN20uk",
    "locationDesc": "US-NJ",
    "attempts": 1142,
    "activations": 1120,
    "qsos": 76262
  },
  {
    "reference": "US-1612",
    "name": "Corson's Inlet State Park",
    "latitude": 39.2131,
    "longitude": -74.6452,
    "grid": "FM29qf",
    "locationDesc": "US-NJ",
    "attempts": 91,
    "activations": 89,
    "qsos": 2844
  },
  {
    "reference": "US-1613",
    "name": "Delaware and Raritan Canal State Park",
    "latitude": 40.3685,
    "longitude": -74.6152,
    "grid": "FN20qi",
    "locationDesc": "US-NJ",
    "attempts": 463,
    "activations": 444,
    "qsos": 11658
  },
  {
    "reference": "US-1614",
    "name": "Double Trouble State Park",
    "latitude": 39.898,
    "longitude": -74.2211,
    "grid": "FM29vv",
    "locationDesc": "US-NJ",
    "attempts": 130,
    "activations": 123,
    "qsos": 4363
  },
  {
    "reference": "US-1615",
    "name": "Thomas Edison Memorial State Park",
    "latitude": 40.562,
    "longitude": -74.3404,
    "grid": "FN20tn",
    "locationDesc": "US-NJ",
    "attempts": 177,
    "activations": 162,
    "qsos": 6619
  },
  {
    "reference": "US-1616",
    "name": "Farny State Park",
    "latitude": 41.0025,
    "longitude": -74.4467,
    "grid": "FN21sa",
    "locationDesc": "US-NJ",
    "attempts": 63,
    "activations": 62,
    "qsos": 1729
  },
  {
    "reference": "US-1617",
    "name": "Fort Mott State Park",
    "latitude": 39.6046,
    "longitude": -75.5524,
    "grid": "FM29fo",
    "locationDesc": "US-NJ",
    "attempts": 104,
    "activations": 99,
    "qsos": 2924
  },
  {
    "reference": "US-1618",
    "name": "Hacklebarney State Park",
    "latitude": 40.7452,
    "longitude": -74.728,
    "grid": "FN20pr",
    "locationDesc": "US-NJ",
    "attempts": 100,
    "activations": 99,
    "qsos": 3379
  },
  {
    "reference": "US-1619",
    "name": "High Point State Park",
    "latitude": 41.32,
    "longitude": -74.6661,
    "grid": "FN21qh",
    "locationDesc": "US-NJ",
    "attempts": 343,
    "activations": 327,
    "qsos": 11515
  },
  {
    "reference": "US-1620",
    "name": "Hopatcong State Park",
    "latitude": 40.9163,
    "longitude": -74.664,
    "grid": "FN20qv",
    "locationDesc": "US-NJ",
    "attempts": 126,
    "activations": 123,
    "qsos": 4563
  },
  {
    "reference": "US-1621",
    "name": "Island Beach State Park",
    "latitude": 39.9041,
    "longitude": -74.0814,
    "grid": "FM29xv",
    "locationDesc": "US-NJ",
    "attempts": 228,
    "activations": 216,
    "qsos": 9613
  },
  {
    "reference": "US-1622",
    "name": "Kittatinny Valley State Park",
    "latitude": 41.0182,
    "longitude": -74.7371,
    "grid": "FN21pa",
    "locationDesc": "US-NJ",
    "attempts": 106,
    "activations": 102,
    "qsos": 3357
  },
  {
    "reference": "US-1623",
    "name": "Liberty State Park",
    "latitude": 40.7036,
    "longitude": -74.0457,
    "grid": "FN20xq",
    "locationDesc": "US-NJ",
    "attempts": 443,
    "activations": 422,
    "qsos": 19394
  },
  {
    "reference": "US-1624",
    "name": "Long Pond Ironworks State Park",
    "latitude": 41.137,
    "longitude": -74.3069,
    "grid": "FN21ud",
    "locationDesc": "US-NJ",
    "attempts": 83,
    "activations": 77,
    "qsos": 2295
  },
  {
    "reference": "US-1625",
    "name": "Monmouth Battlefield State Park",
    "latitude": 40.2561,
    "longitude": -74.3208,
    "grid": "FN20ug",
    "locationDesc": "US-NJ",
    "attempts": 225,
    "activations": 219,
    "qsos": 9342
  },
  {
    "reference": "US-1626",
    "name": "Parvin State Park",
    "latitude": 39.5106,
    "longitude": -75.1328,
    "grid": "FM29km",
    "locationDesc": "US-NJ",
    "attempts": 277,
    "activations": 268,
    "qsos": 8400
  },
  {
    "reference": "US-1627",
    "name": "Pigeon Swamp State Park",
    "latitude": 40.3847,
    "longitude": -74.4833,
    "grid": "FN20sj",
    "locationDesc": "US-NJ",
    "attempts": 56,
    "activations": 55,
    "qsos": 1776
  },
  {
    "reference": "US-1628",
    "name": "Princeton Battlefield State Park",
    "latitude": 40.3288,
    "longitude": -74.6748,
    "grid": "FN20ph",
    "locationDesc": "US-NJ",
    "attempts": 173,
    "activations": 163,
    "qsos": 4381
  },
  {
    "reference": "US-1629",
    "name": "Rancocas State Park",
    "latitude": 40.0037,
    "longitude": -74.821,
    "grid": "FN20oa",
    "locationDesc": "US-NJ",
    "attempts": 190,
    "activations": 178,
    "qsos": 4174
  },
  {
    "reference": "US-1630",
    "name": "Ringwood State Park",
    "latitude": 41.136,
    "longitude": -74.2331,
    "grid": "FN21vd",
    "locationDesc": "US-NJ",
    "attempts": 168,
    "activations": 162,
    "qsos": 5378
  },
  {
    "reference": "US-1631",
    "name": "Stephens State Park",
    "latitude": 40.8688,
    "longitude": -74.8102,
    "grid": "FN20ou",
    "locationDesc": "US-NJ",
    "attempts": 138,
    "activations": 134,
    "qsos": 3748
  },
  {
    "reference": "US-1632",
    "name": "Swartswood State Park",
    "latitude": 41.0746,
    "longitude": -74.8189,
    "grid": "FN21ob",
    "locationDesc": "US-NJ",
    "attempts": 134,
    "activations": 129,
    "qsos": 3790
  },
  {
    "reference": "US-1633",
    "name": "Voorhees State Park",
    "latitude": 40.684,
    "longitude": -74.896,
    "grid": "FN20nq",
    "locationDesc": "US-NJ",
    "attempts": 153,
    "activations": 146,
    "qsos": 4329
  },
  {
    "reference": "US-1634",
    "name": "Washington Crossing State Park",
    "latitude": 40.3077,
    "longitude": -74.8612,
    "grid": "FN20nh",
    "locationDesc": "US-NJ",
    "attempts": 360,
    "activations": 343,
    "qsos": 8857
  },
  {
    "reference": "US-1635",
    "name": "Washington Rock State Park",
    "latitude": 40.6128,
    "longitude": -74.4724,
    "grid": "FN20so",
    "locationDesc": "US-NJ",
    "attempts": 192,
    "activations": 178,
    "qsos": 5659
  },
  {
    "reference": "US-1636",
    "name": "Wawayanda State Park",
    "latitude": 41.1901,
    "longitude": -74.4289,
    "grid": "FN21se",
    "locationDesc": "US-NJ",
    "attempts": 120,
    "activations": 114,
    "qsos": 3586
  },
  {
    "reference": "US-3379",
    "name": "Delaware Water Gap National Recreation Area",
    "latitude": 41.0706,
    "longitude": -75.0169,
    "grid": "FN21lb",
    "locationDesc": "US-NJ,US-PA",
    "attempts": 273,
    "activations": 254,
    "qsos": 7966
  },
  {
    "reference": "US-4556",
    "name": "Appalachian Trail National Scenic Trail",
    "latitude": 34.6267,
    "longitude": -84.1937,
    "grid": "EM74vp",
    "locationDesc": "US-CT,US-GA,US-MA,US-MD,US-ME,US-NC,US-NH,US-NJ,US-NY,US-PA,US-TN,US-VA,US-VT,US-WV",
    "attempts": 5694,
    "activations": 5461,
    "qsos": 200585
  },
  {
    "reference": "US-4582",
    "name": "Washington-Rochambeau Revolutionary Route National Historic Trail",
    "latitude": 41.312,
    "longitude": -73.9709,
    "grid": "FN31ah",
    "locationDesc": "US-CT,US-DC,US-DE,US-MA,US-MD,US-NJ,US-NY,US-PA,US-RI,US-VA",
    "attempts": 2522,
    "activations": 2475,
    "qsos": 102891
  },
  {
    "reference": "US-4991",
    "name": "Abram S. Hewitt State Forest",
    "latitude": 41.1575,
    "longitude": -74.3675,
    "grid": "FN21td",
    "locationDesc": "US-NJ",
    "attempts": 47,
    "activations": 47,
    "qsos": 1220
  },
  {
    "reference": "US-4992",
    "name": "Bass River State Forest",
    "latitude": 39.6252,
    "longitude": -74.4261,
    "grid": "FM29sp",
    "locationDesc": "US-NJ",
    "attempts": 100,
    "activations": 95,
    "qsos": 2920
  },
  {
    "reference": "US-4993",
    "name": "Belleplain State Forest",
    "latitude": 39.2467,
    "longitude": -74.8584,
    "grid": "FM29nf",
    "locationDesc": "US-NJ",
    "attempts": 146,
    "activations": 135,
    "qsos": 6009
  },
  {
    "reference": "US-4994",
    "name": "Brendan T. Byrne State Forest",
    "latitude": 39.895,
    "longitude": -74.5751,
    "grid": "FM29rv",
    "locationDesc": "US-NJ",
    "attempts": 130,
    "activations": 117,
    "qsos": 5161
  },
  {
    "reference": "US-4995",
    "name": "Jenny Jump State Forest",
    "latitude": 40.9128,
    "longitude": -74.9229,
    "grid": "FN20mv",
    "locationDesc": "US-NJ",
    "attempts": 110,
    "activations": 109,
    "qsos": 3837
  },
  {
    "reference": "US-4996",
    "name": "Norvin Green State Forest",
    "latitude": 41.0557,
    "longitude": -74.3415,
    "grid": "FN21tb",
    "locationDesc": "US-NJ",
    "attempts": 62,
    "activations": 59,
    "qsos": 1511
  },
  {
    "reference": "US-4997",
    "name": "Penn State Forest",
    "latitude": 39.744,
    "longitude": -74.4599,
    "grid": "FM29sr",
    "locationDesc": "US-NJ",
    "attempts": 24,
    "activations": 24,
    "qsos": 793
  },
  {
    "reference": "US-4998",
    "name": "Ramapo Mountain State Forest",
    "latitude": 41.0479,
    "longitude": -74.2607,
    "grid": "FN21ub",
    "locationDesc": "US-NJ",
    "attempts": 139,
    "activations": 133,
    "qsos": 3981
  },
  {
    "reference": "US-4999",
    "name": "Stokes State Forest",
    "latitude": 41.2284,
    "longitude": -74.7524,
    "grid": "FN21of",
    "locationDesc": "US-NJ",
    "attempts": 221,
    "activations": 213,
    "qsos": 8309
  },
  {
    "reference": "US-5000",
    "name": "Wharton State Forest",
    "latitude": 39.7393,
    "longitude": -74.729,
    "grid": "FM29pr",
    "locationDesc": "US-NJ",
    "attempts": 189,
    "activations": 182,
    "qsos": 6834
  },
  {
    "reference": "US-5001",
    "name": "Worthington State Forest",
    "latitude": 41.0045,
    "longitude": -75.1043,
    "grid": "FN21ka",
    "locationDesc": "US-NJ",
    "attempts": 137,
    "activations": 129,
    "qsos": 3485
  },
  {
    "reference": "US-6461",
    "name": "Spruce Run State Recreation Area",
    "latitude": 40.6616,
    "longitude": -74.925,
    "grid": "FN20mp",
    "locationDesc": "US-NJ",
    "attempts": 200,
    "activations": 190,
    "qsos": 6456
  },
  {
    "reference": "US-6462",
    "name": "Garret Mountain Reservation State Park",
    "latitude": 40.9006,
    "longitude": -74.1806,
    "grid": "FN20vv",
    "locationDesc": "US-NJ",
    "attempts": 1133,
    "activations": 1101,
    "qsos": 42445
  },
  {
    "reference": "US-6467",
    "name": "Mad Horse Creek Wildlife Management Area",
    "latitude": 39.4634,
    "longitude": -75.4652,
    "grid": "FM29gl",
    "locationDesc": "US-NJ",
    "attempts": 39,
    "activations": 38,
    "qsos": 1771
  },
  {
    "reference": "US-6544",
    "name": "New Jersey Coastal State Trail",
    "latitude": 40.4267,
    "longitude": -73.985,
    "grid": "FN30ak",
    "locationDesc": "US-NJ",
    "attempts": 2616,
    "activations": 2564,
    "qsos": 142004
  },
  {
    "reference": "US-6609",
    "name": "Pinelands Preserve National Conservation Area",
    "latitude": 39.6462,
    "longitude": -74.6461,
    "grid": "FM29qp",
    "locationDesc": "US-NJ",
    "attempts": 1265,
    "activations": 1241,
    "qsos": 52698
  },
  {
    "reference": "US-7504",
    "name": "Assunpink Wildlife Management Area",
    "latitude": 40.2006,
    "longitude": -74.5041,
    "grid": "FN20re",
    "locationDesc": "US-NJ",
    "attempts": 146,
    "activations": 146,
    "qsos": 4806
  },
  {
    "reference": "US-7505",
    "name": "Round Valley State Recreation Area",
    "latitude": 40.6271,
    "longitude": -74.8517,
    "grid": "FN20np",
    "locationDesc": "US-NJ",
    "attempts": 235,
    "activations": 225,
    "qsos": 6553
  },
  {
    "reference": "US-7506",
    "name": "Tall Pines Preserve State Conservation Area",
    "latitude": 39.7799,
    "longitude": -75.1388,
    "grid": "FM29ks",
    "locationDesc": "US-NJ",
    "attempts": 112,
    "activations": 107,
    "qsos": 3386
  },
  {
    "reference": "US-7507",
    "name": "Warren Grove State Recreation Area",
    "latitude": 39.7553,
    "longitude": -74.4073,
    "grid": "FM29ts",
    "locationDesc": "US-NJ",
    "attempts": 25,
    "activations": 24,
    "qsos": 803
  },
  {
    "reference": "US-8030",
    "name": "Absecon Wildlife Management Area",
    "latitude": 39.4277,
    "longitude": -74.3836,
    "grid": "FM29tk",
    "locationDesc": "US-NJ",
    "attempts": 103,
    "activations": 102,
    "qsos": 3537
  },
  {
    "reference": "US-8031",
    "name": "Bear Swamp Wildlife Management Area",
    "latitude": 41.1353,
    "longitude": -74.7774,
    "grid": "FN21od",
    "locationDesc": "US-NJ",
    "attempts": 39,
    "activations": 39,
    "qsos": 1122
  },
  {
    "reference": "US-8032",
    "name": "Black River Wildlife Management Area",
    "latitude": 40.8074,
    "longitude": -74.6671,
    "grid": "FN20pt",
    "locationDesc": "US-NJ",
    "attempts": 130,
    "activations": 126,
    "qsos": 4098
  },
  {
    "reference": "US-8033",
    "name": "Buckshutem Wildlife Management Area",
    "latitude": 39.415,
    "longitude": -75.1531,
    "grid": "FM29kj",
    "locationDesc": "US-NJ",
    "attempts": 32,
    "activations": 31,
    "qsos": 947
  },
  {
    "reference": "US-8034",
    "name": "Cape May Coastal Wetlands Wildlife Management Area",
    "latitude": 39.0572,
    "longitude": -74.824,
    "grid": "FM29ob",
    "locationDesc": "US-NJ",
    "attempts": 60,
    "activations": 55,
    "qsos": 1770
  },
  {
    "reference": "US-8035",
    "name": "Colliers Mill Wildlife Management Area",
    "latitude": 40.0805,
    "longitude": -74.4319,
    "grid": "FN20sb",
    "locationDesc": "US-NJ",
    "attempts": 65,
    "activations": 61,
    "qsos": 1862
  },
  {
    "reference": "US-8036",
    "name": "Dennis Creek Wildlife Management Area",
    "latitude": 39.1792,
    "longitude": -74.8515,
    "grid": "FM29ne",
    "locationDesc": "US-NJ",
    "attempts": 34,
    "activations": 34,
    "qsos": 1474
  },
  {
    "reference": "US-8037",
    "name": "Dix Wildlife Management Area",
    "latitude": 39.3629,
    "longitude": -75.318,
    "grid": "FM29ii",
    "locationDesc": "US-NJ",
    "attempts": 47,
    "activations": 47,
    "qsos": 1781
  },
  {
    "reference": "US-8038",
    "name": "Egg Island Wildlife Management Area",
    "latitude": 39.2369,
    "longitude": -75.0965,
    "grid": "FM29kf",
    "locationDesc": "US-NJ",
    "attempts": 21,
    "activations": 21,
    "qsos": 874
  },
  {
    "reference": "US-8039",
    "name": "Forked River Mt Wildlife Management Area",
    "latitude": 39.8079,
    "longitude": -74.2757,
    "grid": "FM29ut",
    "locationDesc": "US-NJ",
    "attempts": 32,
    "activations": 31,
    "qsos": 799
  },
  {
    "reference": "US-8040",
    "name": "Greenwood Forest Wildlife Management Area",
    "latitude": 39.8335,
    "longitude": -74.3851,
    "grid": "FM29tu",
    "locationDesc": "US-NJ",
    "attempts": 37,
    "activations": 36,
    "qsos": 1015
  },
  {
    "reference": "US-8041",
    "name": "Hammonton Creek Wildlife Management Area",
    "latitude": 39.6051,
    "longitude": -74.7505,
    "grid": "FM29oo",
    "locationDesc": "US-NJ",
    "attempts": 53,
    "activations": 51,
    "qsos": 2034
  },
  {
    "reference": "US-8042",
    "name": "Heislerville Wildlife Management Area",
    "latitude": 39.2033,
    "longitude": -75.0139,
    "grid": "FM29le",
    "locationDesc": "US-NJ",
    "attempts": 43,
    "activations": 41,
    "qsos": 2357
  },
  {
    "reference": "US-8043",
    "name": "Makepeace Lake Wildlife Management Area",
    "latitude": 39.5572,
    "longitude": -74.7402,
    "grid": "FM29pn",
    "locationDesc": "US-NJ",
    "attempts": 61,
    "activations": 60,
    "qsos": 3287
  },
  {
    "reference": "US-8044",
    "name": "Manchester Wildlife Management Area",
    "latitude": 39.9969,
    "longitude": -74.4194,
    "grid": "FM29sx",
    "locationDesc": "US-NJ",
    "attempts": 35,
    "activations": 35,
    "qsos": 1022
  },
  {
    "reference": "US-8045",
    "name": "Millville Wildlife Management Area",
    "latitude": 39.3211,
    "longitude": -75.0633,
    "grid": "FM29lh",
    "locationDesc": "US-NJ",
    "attempts": 28,
    "activations": 28,
    "qsos": 771
  },
  {
    "reference": "US-8046",
    "name": "New Sweden Wildlife Management Area",
    "latitude": 39.2977,
    "longitude": -75.2477,
    "grid": "FM29jh",
    "locationDesc": "US-NJ",
    "attempts": 21,
    "activations": 21,
    "qsos": 937
  },
  {
    "reference": "US-8047",
    "name": "Paulinskill Wildlife Management Area",
    "latitude": 41.072,
    "longitude": -74.7899,
    "grid": "FN21ob",
    "locationDesc": "US-NJ",
    "attempts": 57,
    "activations": 56,
    "qsos": 1831
  },
  {
    "reference": "US-8048",
    "name": "Pequest Wildlife Management Area",
    "latitude": 40.8364,
    "longitude": -74.9446,
    "grid": "FN20mu",
    "locationDesc": "US-NJ",
    "attempts": 119,
    "activations": 116,
    "qsos": 3323
  },
  {
    "reference": "US-8049",
    "name": "Rockaway River Wildlife Management Area",
    "latitude": 40.977,
    "longitude": -74.5471,
    "grid": "FN20rx",
    "locationDesc": "US-NJ",
    "attempts": 51,
    "activations": 48,
    "qsos": 1011
  },
  {
    "reference": "US-8050",
    "name": "Salem River Wildlife Management Area",
    "latitude": 39.6697,
    "longitude": -75.4693,
    "grid": "FM29gq",
    "locationDesc": "US-NJ",
    "attempts": 96,
    "activations": 95,
    "qsos": 2601
  },
  {
    "reference": "US-8051",
    "name": "Sparta Mountain Wildlife Management Area",
    "latitude": 41.0506,
    "longitude": -74.5511,
    "grid": "FN21rb",
    "locationDesc": "US-NJ",
    "attempts": 47,
    "activations": 45,
    "qsos": 1487
  },
  {
    "reference": "US-8052",
    "name": "Stafford Forge Wildlife Management Area",
    "latitude": 39.6683,
    "longitude": -74.321,
    "grid": "FM29uq",
    "locationDesc": "US-NJ",
    "attempts": 64,
    "activations": 64,
    "qsos": 1985
  },
  {
    "reference": "US-8053",
    "name": "Swan Bay Wildlife Management Area",
    "latitude": 39.5807,
    "longitude": -74.5115,
    "grid": "FM29rn",
    "locationDesc": "US-NJ",
    "attempts": 40,
    "activations": 39,
    "qsos": 1748
  },
  {
    "reference": "US-8054",
    "name": "Thundergut Pond Wildlife Management Area",
    "latitude": 39.5326,
    "longitude": -75.3385,
    "grid": "FM29hm",
    "locationDesc": "US-NJ",
    "attempts": 43,
    "activations": 43,
    "qsos": 1763
  },
  {
    "reference": "US-8055",
    "name": "Tuckahoe Wildlife Management Area",
    "latitude": 39.308,
    "longitude": -74.7194,
    "grid": "FM29ph",
    "locationDesc": "US-NJ",
    "attempts": 39,
    "activations": 39,
    "qsos": 1553
  },
  {
    "reference": "US-8056",
    "name": "Turkey Swamp Wildlife Management Area",
    "latitude": 40.188,
    "longitude": -74.3176,
    "grid": "FN20ue",
    "locationDesc": "US-NJ",
    "attempts": 78,
    "activations": 76,
    "qsos": 2321
  },
  {
    "reference": "US-8057",
    "name": "Union Lake Wildlife Management Area",
    "latitude": 39.4343,
    "longitude": -75.0983,
    "grid": "FM29kk",
    "locationDesc": "US-NJ",
    "attempts": 84,
    "activations": 82,
    "qsos": 2477
  },
  {
    "reference": "US-8058",
    "name": "White Oak Branch Wildlife Management Area",
    "latitude": 39.6041,
    "longitude": -74.9953,
    "grid": "FM29mo",
    "locationDesc": "US-NJ",
    "attempts": 52,
    "activations": 50,
    "qsos": 1856
  },
  {
    "reference": "US-8059",
    "name": "Wildcat Ridge Wildlife Management Area",
    "latitude": 40.9445,
    "longitude": -74.4953,
    "grid": "FN20sw",
    "locationDesc": "US-NJ",
    "attempts": 102,
    "activations": 99,
    "qsos": 3445
  },
  {
    "reference": "US-8060",
    "name": "Winslow Wildlife Management Area",
    "latitude": 39.6493,
    "longitude": -74.9204,
    "grid": "FM29mp",
    "locationDesc": "US-NJ",
    "attempts": 61,
    "activations": 57,
    "qsos": 2863
  },
  {
    "reference": "US-8061",
    "name": "Ellis Island National Historic Site",
    "latitude": 40.6995,
    "longitude": -74.0396,
    "grid": "FN20xq",
    "locationDesc": "US-NJ,US-NY",
    "attempts": 9,
    "activations": 9,
    "qsos": 191
  },
  {
    "reference": "US-8319",
    "name": "Palisades Interstate Park",
    "latitude": 40.953,
    "longitude": -73.9207,
    "grid": "FN30aw",
    "locationDesc": "US-NJ,US-NY",
    "attempts": 748,
    "activations": 714,
    "qsos": 27328
  },
  {
    "reference": "US-11337",
    "name": "Hamburg Mountain Wildlife Management Area",
    "latitude": 41.1064,
    "longitude": -74.5587,
    "grid": "FN21rc",
    "locationDesc": "US-NJ",
    "attempts": 85,
    "activations": 83,
    "qsos": 2398
  },
  {
    "reference": "US-11338",
    "name": "Stow Creek State Park",
    "latitude": 39.4441,
    "longitude": -75.3984,
    "grid": "FM29hk",
    "locationDesc": "US-NJ",
    "attempts": 51,
    "activations": 50,
    "qsos": 1943
  },
  {
    "reference": "US-11340",
    "name": "Higbee Beach Wildlife Management Area",
    "latitude": 38.9614,
    "longitude": -74.9607,
    "grid": "FM28mx",
    "locationDesc": "US-NJ",
    "attempts": 45,
    "activations": 42,
    "qsos": 1129
  },
  {
    "reference": "US-11863",
    "name": "Butterfly Bogs Wildlife Management Area",
    "latitude": 40.0965,
    "longitude": -74.3028,
    "grid": "FN20uc",
    "locationDesc": "US-NJ",
    "attempts": 23,
    "activations": 21,
    "qsos": 397
  },
  {
    "reference": "US-11964",
    "name": "Peaslee Wildlife Management Area",
    "latitude": 39.3236,
    "longitude": -74.8257,
    "grid": "FM29oh",
    "locationDesc": "US-NJ",
    "attempts": 28,
    "activations": 28,
    "qsos": 821
  },
  {
    "reference": "US-11965",
    "name": "Glassboro Wildlife Management Area",
    "latitude": 39.6813,
    "longitude": -75.074,
    "grid": "FM29lq",
    "locationDesc": "US-NJ",
    "attempts": 143,
    "activations": 138,
    "qsos": 5049
  },
  {
    "reference": "US-11988",
    "name": "Cohansey River Wildlife Management Area",
    "latitude": 39.394,
    "longitude": -75.21,
    "grid": "FM29jj",
    "locationDesc": "US-NJ",
    "attempts": 42,
    "activations": 39,
    "qsos": 1520
  },
  {
    "reference": "US-11989",
    "name": "Great Bay Boulevard Wildlife Management Area",
    "latitude": 39.54,
    "longitude": -74.322,
    "grid": "FM29um",
    "locationDesc": "US-NJ",
    "attempts": 54,
    "activations": 54,
    "qsos": 2802
  },
  {
    "reference": "US-11990",
    "name": "Harrisonville Lake Wildlife Management Area",
    "latitude": 39.682,
    "longitude": -75.266,
    "grid": "FM29iq",
    "locationDesc": "US-NJ",
    "attempts": 35,
    "activations": 35,
    "qsos": 1431
  },
  {
    "reference": "US-11991",
    "name": "South Branch Wildlife Management Area",
    "latitude": 40.513,
    "longitude": -74.795,
    "grid": "FN20om",
    "locationDesc": "US-NJ",
    "attempts": 127,
    "activations": 125,
    "qsos": 4152
  },
  {
    "reference": "US-11992",
    "name": "Whiting State Conservation Area",
    "latitude": 39.971,
    "longitude": -74.342,
    "grid": "FM29tx",
    "locationDesc": "US-NJ",
    "attempts": 18,
    "activations": 17,
    "qsos": 492
  },
  {
    "reference": "US-11993",
    "name": "Clarks Pond Wildlife Management Area",
    "latitude": 39.391,
    "longitude": -75.209,
    "grid": "FM29jj",
    "locationDesc": "US-NJ",
    "attempts": 40,
    "activations": 40,
    "qsos": 1475
  },
  {
    "reference": "US-12099",
    "name": "Alexauken Creek Wildlife Management Area",
    "latitude": 40.397,
    "longitude": -74.87,
    "grid": "FN20nj",
    "locationDesc": "US-NJ",
    "attempts": 67,
    "activations": 67,
    "qsos": 1263
  },
  {
    "reference": "US-12100",
    "name": "Amwell Lake Wildlife Management Area",
    "latitude": 40.4,
    "longitude": -74.844,
    "grid": "FN20nj",
    "locationDesc": "US-NJ",
    "attempts": 69,
    "activations": 69,
    "qsos": 1939
  },
  {
    "reference": "US-12101",
    "name": "Clinton Wildlife Management Area",
    "latitude": 40.656,
    "longitude": -74.963,
    "grid": "FN20mp",
    "locationDesc": "US-NJ",
    "attempts": 61,
    "activations": 61,
    "qsos": 1695
  },
  {
    "reference": "US-12102",
    "name": "Ken Lockwood Gorge Wildlife Management Area",
    "latitude": 40.688,
    "longitude": -74.88,
    "grid": "FN20nq",
    "locationDesc": "US-NJ",
    "attempts": 51,
    "activations": 51,
    "qsos": 968
  },
  {
    "reference": "US-12103",
    "name": "Lockatong Wildlife Management Area",
    "latitude": 40.496,
    "longitude": -75.001,
    "grid": "FN20ll",
    "locationDesc": "US-NJ",
    "attempts": 27,
    "activations": 25,
    "qsos": 723
  },
  {
    "reference": "US-12104",
    "name": "Pohatcong Creek Wildlife Management Area",
    "latitude": 40.606,
    "longitude": -75.189,
    "grid": "FN20jo",
    "locationDesc": "US-NJ",
    "attempts": 22,
    "activations": 22,
    "qsos": 689
  },
  {
    "reference": "US-12105",
    "name": "Rockport Wildlife Management Area",
    "latitude": 40.829,
    "longitude": -74.872,
    "grid": "FN20nt",
    "locationDesc": "US-NJ",
    "attempts": 89,
    "activations": 89,
    "qsos": 2477
  },
  {
    "reference": "US-12168",
    "name": "Medford Wildlife Management Area",
    "latitude": 39.922,
    "longitude": -74.841,
    "grid": "FM29nw",
    "locationDesc": "US-NJ",
    "attempts": 39,
    "activations": 39,
    "qsos": 931
  },
  {
    "reference": "US-12644",
    "name": "Berkshire Valley Wildlife Management Area",
    "latitude": 40.9089,
    "longitude": -74.6364,
    "grid": "FN20qv",
    "locationDesc": "US-NJ",
    "attempts": 49,
    "activations": 49,
    "qsos": 3551
  },
  {
    "reference": "US-12645",
    "name": "Flatbrook Roy Wildlife Management Area",
    "latitude": 41.1881,
    "longitude": -74.8505,
    "grid": "FN21ne",
    "locationDesc": "US-NJ",
    "attempts": 11,
    "activations": 11,
    "qsos": 791
  },
  {
    "reference": "US-13057",
    "name": "Beaver Swamp Wildlife Management Area",
    "latitude": 39.13,
    "longitude": -74.802,
    "grid": "FM29od",
    "locationDesc": "US-NJ",
    "attempts": 8,
    "activations": 8,
    "qsos": 342
  },
  {
    "reference": "US-13059",
    "name": "Abbots Meadow Wildlife Management Area",
    "latitude": 39.52,
    "longitude": -75.507,
    "grid": "FM29fm",
    "locationDesc": "US-NJ",
    "attempts": 16,
    "activations": 16,
    "qsos": 479
  },
  {
    "reference": "US-13060",
    "name": "Elmer Lake Wildlife Management Area",
    "latitude": 39.597,
    "longitude": -75.165,
    "grid": "FM29ko",
    "locationDesc": "US-NJ",
    "attempts": 60,
    "activations": 60,
    "qsos": 2756
  },
  {
    "reference": "US-13061",
    "name": "Gum Tree Corner Wildlife Management Area",
    "latitude": 39.44,
    "longitude": -75.386,
    "grid": "FM29hk",
    "locationDesc": "US-NJ",
    "attempts": 14,
    "activations": 14,
    "qsos": 437
  },
  {
    "reference": "US-13117",
    "name": "D.O.D. Ponds Wildlife Management Area",
    "latitude": 39.747,
    "longitude": -75.46,
    "grid": "FM29gr",
    "locationDesc": "US-NJ",
    "attempts": 8,
    "activations": 8,
    "qsos": 359
  },
  {
    "reference": "US-13147",
    "name": "Andalora Wildlife Management Area",
    "latitude": 39.8585,
    "longitude": -75.1179,
    "grid": "FM29ku",
    "locationDesc": "US-NJ",
    "attempts": 9,
    "activations": 9,
    "qsos": 279
  },
  {
    "reference": "US-13148",
    "name": "Baldwin Lake Wildlife Management Area",
    "latitude": 40.3409,
    "longitude": -74.7815,
    "grid": "FN20oi",
    "locationDesc": "US-NJ",
    "attempts": 5,
    "activations": 5,
    "qsos": 152
  },
  {
    "reference": "US-13149",
    "name": "Beaver Brook Wildlife Management Area",
    "latitude": 40.8595,
    "longitude": -75.0336,
    "grid": "FN20lu",
    "locationDesc": "US-NJ",
    "attempts": 9,
    "activations": 9,
    "qsos": 182
  },
  {
    "reference": "US-13150",
    "name": "Belvidere Access Wildlife Management Area",
    "latitude": 40.8282,
    "longitude": -75.0822,
    "grid": "FN20lt",
    "locationDesc": "US-NJ",
    "attempts": 13,
    "activations": 13,
    "qsos": 366
  },
  {
    "reference": "US-13254",
    "name": "Van Nest Refuge Wildlife Management Area",
    "latitude": 40.2691,
    "longitude": -74.6715,
    "grid": "FN20pg",
    "locationDesc": "US-NJ",
    "attempts": 8,
    "activations": 8,
    "qsos": 288
  },
  {
    "reference": "US-13255",
    "name": "Hancock House Historic Site",
    "latitude": 39.5081,
    "longitude": -75.4603,
    "grid": "FM29gm",
    "locationDesc": "US-NJ",
    "attempts": 2,
    "activations": 2,
    "qsos": 47
  },
  {
    "reference": "US-13256",
    "name": "Menantico Ponds Wildlife Management Area",
    "latitude": 39.3677,
    "longitude": -74.9974,
    "grid": "FM29mi",
    "locationDesc": "US-NJ",
    "attempts": 2,
    "activations": 2,
    "qsos": 29
  }
]
